{
  "articleNo": "F 026 407 006",
  "articleId": 6926839,
  "supplier": "BOSCH",
  "product": "Oil Filter",
  "vehicles": [
    {
      "vehicleId": 1,
      "modelId": 5598,
      "manufacturerName": "OPEL",
      "modelName": "CORSA D (S07)",
      "typeEngineName": "1.4 (L08, L68)",
      "constructionIntervalStart": "2006-07-01",
      "constructionIntervalEnd": "2014-08-01"
    },
    {
      "vehicleId": 850,
      "modelId": 9017,
      "manufacturerName": "OPEL",
      "modelName": "ASTRA J Sports Tourer (P10)",
      "typeEngineName": "1.4 (35)",
      "constructionIntervalStart": "2010-10-01",
      "constructionIntervalEnd": "2015-10-01"
    },
    {
      "vehicleId": 853,
      "modelId": 9017,
      "manufacturerName": "OPEL",
      "modelName": "ASTRA J Sports Tourer (P10)",
      "typeEngineName": "1.6 (35)",
      "constructionIntervalStart": "2010-10-01",
      "constructionIntervalEnd": "2015-10-01"
    },
    {
      "vehicleId": 884,
      "modelId": 9017,
      "manufacturerName": "OPEL",
      "modelName": "ASTRA J Sports Tourer (P10)",
      "typeEngineName": "1.4 Turbo (35)",
      "constructionIntervalStart": "2010-10-01",
      "constructionIntervalEnd": "2015-10-01"
    },
    {
      "vehicleId": 908,
      "modelId": 9017,
      "manufacturerName": "OPEL",
      "modelName": "ASTRA J Sports Tourer (P10)",
      "typeEngineName": "1.4 Turbo (35)",
      "constructionIntervalStart": "2010-10-01",
      "constructionIntervalEnd": "2015-10-01"
    },
    {
      "vehicleId": 927,
      "modelId": 9017,
      "manufacturerName": "OPEL",
      "modelName": "ASTRA J Sports Tourer (P10)",
      "typeEngineName": "1.6 Turbo (35)",
      "constructionIntervalStart": "2010-10-01",
      "constructionIntervalEnd": "2015-10-01"
    },
    {
      "vehicleId": 2360,
      "modelId": 9036,
      "manufacturerName": "VAUXHALL",
      "modelName": "ASTRA Mk VI (J) Estate (P10)",
      "typeEngineName": "1.4",
      "constructionIntervalStart": "2010-10-01",
      "constructionIntervalEnd": "2015-10-01"
    },
    {
      "vehicleId": 2370,
      "modelId": 9036,
      "manufacturerName": "VAUXHALL",
      "modelName": "ASTRA Mk VI (J) Estate (P10)",
      "typeEngineName": "1.6",
      "constructionIntervalStart": "2010-10-01",
      "constructionIntervalEnd": "2015-10-01"
    },
    {
      "vehicleId": 2376,
      "modelId": 9036,
      "manufacturerName": "VAUXHALL",
      "modelName": "ASTRA Mk VI (J) Estate (P10)",
      "typeEngineName": "1.4 Turbo",
      "constructionIntervalStart": "2010-10-01",
      "constructionIntervalEnd": "2015-10-01"
    },
    {
      "vehicleId": 9157,
      "modelId": 5598,
      "manufacturerName": "OPEL",
      "modelName": "CORSA D (S07)",
      "typeEngineName": "1.0 (L08, L68)",
      "constructionIntervalStart": "2009-12-01",
      "constructionIntervalEnd": "2014-08-01"
    },
    {
      "vehicleId": 9160,
      "modelId": 8261,
      "manufacturerName": "OPEL",
      "modelName": "ASTRA J (P10)",
      "typeEngineName": "1.4 Turbo (68)",
      "constructionIntervalStart": "2010-10-01",
      "constructionIntervalEnd": "2015-10-01"
    },
    {
      "vehicleId": 9173,
      "modelId": 9180,
      "manufacturerName": "OPEL",
      "modelName": "CORSA D Hatchback Van (S07)",
      "typeEngineName": "1.0 (L08)",
      "constructionIntervalStart": "2010-01-01",
      "constructionIntervalEnd": "2014-08-01"
    },
    {
      "vehicleId": 9174,
      "modelId": 9180,
      "manufacturerName": "OPEL",
      "modelName": "CORSA D Hatchback Van (S07)",
      "typeEngineName": "1.2 (L08)",
      "constructionIntervalStart": "2010-01-01",
      "constructionIntervalEnd": "2014-08-01"
    },
    {
      "vehicleId": 9253,
      "modelId": 9184,
      "manufacturerName": "OPEL",
      "modelName": "ZAFIRA B Box Body/MPV (A05)",
      "typeEngineName": "1.8 VAN (M75)",
      "constructionIntervalStart": "2005-07-01",
      "constructionIntervalEnd": "2015-04-01"
    },
    {
      "vehicleId": 9294,
      "modelId": 9180,
      "manufacturerName": "OPEL",
      "modelName": "CORSA D Hatchback Van (S07)",
      "typeEngineName": "1.2 (L08)",
      "constructionIntervalStart": "2010-06-01",
      "constructionIntervalEnd": "2014-08-01"
    },
    {
      "vehicleId": 10446,
      "modelId": 5598,
      "manufacturerName": "OPEL",
      "modelName": "CORSA D (S07)",
      "typeEngineName": "1.6 Turbo (L08, L68)",
      "constructionIntervalStart": "2011-06-01",
      "constructionIntervalEnd": "2014-08-01"
    },
    {
      "vehicleId": 10447,
      "modelId": 5598,
      "manufacturerName": "OPEL",
      "modelName": "CORSA D (S07)",
      "typeEngineName": "1.2 LPG (L08, L68)",
      "constructionIntervalStart": "2011-06-01",
      "constructionIntervalEnd": "2014-08-01"
    },
    {
      "vehicleId": 10448,
      "modelId": 8549,
      "manufacturerName": "OPEL",
      "modelName": "MERIVA B MPV (S10)",
      "typeEngineName": "1.4 LPG (75)",
      "constructionIntervalStart": "2011-06-01",
      "constructionIntervalEnd": "2017-03-01"
    },
    {
      "vehicleId": 10457,
      "modelId": 9628,
      "manufacturerName": "OPEL",
      "modelName": "ASTRA J GTC",
      "typeEngineName": "1.4 (08)",
      "constructionIntervalStart": "2011-10-01",
      "constructionIntervalEnd": "2013-11-01"
    },
    {
      "vehicleId": 10474,
      "modelId": 9628,
      "manufacturerName": "OPEL",
      "modelName": "ASTRA J GTC",
      "typeEngineName": "1.6 Turbo (08)",
      "constructionIntervalStart": "2011-10-01",
      "constructionIntervalEnd": "2013-06-01"
    },
    {
      "vehicleId": 10542,
      "modelId": 8301,
      "manufacturerName": "VAUXHALL",
      "modelName": "ASTRA Mk VI (J) (P10)",
      "typeEngineName": "1.4 Turbo",
      "constructionIntervalStart": "2010-08-01",
      "constructionIntervalEnd": "2015-10-01"
    },
    {
      "vehicleId": 11273,
      "modelId": 9709,
      "manufacturerName": "VAUXHALL",
      "modelName": "ASTRA Mk VI (J) GTC (P10)",
      "typeEngineName": "1.6",
      "constructionIntervalStart": "2011-10-01",
      "constructionIntervalEnd": "2018-10-01"
    },
    {
      "vehicleId": 11931,
      "modelId": 9738,
      "manufacturerName": "VAUXHALL",
      "modelName": "ZAFIRA Mk III (P12)",
      "typeEngineName": "1.6 CNG (75)",
      "constructionIntervalStart": "2011-10-01",
      "constructionIntervalEnd": "2018-08-01"
    },
    {
      "vehicleId": 11932,
      "modelId": 9738,
      "manufacturerName": "VAUXHALL",
      "modelName": "ZAFIRA Mk III (P12)",
      "typeEngineName": "1.8 (75)",
      "constructionIntervalStart": "2011-10-01",
      "constructionIntervalEnd": "2018-08-01"
    },
    {
      "vehicleId": 11934,
      "modelId": 9738,
      "manufacturerName": "VAUXHALL",
      "modelName": "ZAFIRA Mk III (P12)",
      "typeEngineName": "1.8 (75)",
      "constructionIntervalStart": "2011-10-01",
      "constructionIntervalEnd": "2018-08-01"
    },
    {
      "vehicleId": 12034,
      "modelId": 5598,
      "manufacturerName": "OPEL",
      "modelName": "CORSA D (S07)",
      "typeEngineName": "1.2 LPG (L08, L68)",
      "constructionIntervalStart": "2011-06-01",
      "constructionIntervalEnd": "2014-08-01"
    },
    {
      "vehicleId": 13949,
      "modelId": 9017,
      "manufacturerName": "OPEL",
      "modelName": "ASTRA J Sports Tourer (P10)",
      "typeEngineName": "1.4 LPG (35)",
      "constructionIntervalStart": "2011-12-01",
      "constructionIntervalEnd": "2015-10-01"
    },
    {
      "vehicleId": 13950,
      "modelId": 8261,
      "manufacturerName": "OPEL",
      "modelName": "ASTRA J (P10)",
      "typeEngineName": "1.4 LPG (68)",
      "constructionIntervalStart": "2012-01-01",
      "constructionIntervalEnd": "2015-10-01"
    },
    {
      "vehicleId": 13952,
      "modelId": 9628,
      "manufacturerName": "OPEL",
      "modelName": "ASTRA J GTC",
      "typeEngineName": "1.8 (08)",
      "constructionIntervalStart": "2011-10-01",
      "constructionIntervalEnd": "2013-10-01"
    },
    {
      "vehicleId": 18886,
      "modelId": 5425,
      "manufacturerName": "OPEL",
      "modelName": "ZAFIRA / ZAFIRA FAMILY B (A05)",
      "typeEngineName": "1.8 (M75)",
      "constructionIntervalStart": "2005-07-01",
      "constructionIntervalEnd": "2015-04-01"
    },
    {
      "vehicleId": 19268,
      "modelId": 4871,
      "manufacturerName": "OPEL",
      "modelName": "VECTRA C GTS (Z02)",
      "typeEngineName": "1.8 (F68)",
      "constructionIntervalStart": "2005-08-01",
      "constructionIntervalEnd": "2008-08-01"
    },
    {
      "vehicleId": 19281,
      "modelId": 4865,
      "manufacturerName": "OPEL",
      "modelName": "VECTRA C (Z02)",
      "typeEngineName": "1.8 (F69)",
      "constructionIntervalStart": "2005-08-01",
      "constructionIntervalEnd": "2008-08-01"
    },
    {
      "vehicleId": 19317,
      "modelId": 5057,
      "manufacturerName": "OPEL",
      "modelName": "VECTRA C Estate (Z02)",
      "typeEngineName": "1.8 (F35)",
      "constructionIntervalStart": "2005-08-01",
      "constructionIntervalEnd": "2008-08-01"
    },
    {
      "vehicleId": 19362,
      "modelId": 5453,
      "manufacturerName": "OPEL",
      "modelName": "ASTRA H TwinTop (A04)",
      "typeEngineName": "1.8 (L67)",
      "constructionIntervalStart": "2005-09-01",
      "constructionIntervalEnd": "2010-10-01"
    },
    {
      "vehicleId": 19427,
      "modelId": 5098,
      "manufacturerName": "OPEL",
      "modelName": "ASTRA H (A04)",
      "typeEngineName": "1.8 (L48)",
      "constructionIntervalStart": "2006-01-01",
      "constructionIntervalEnd": "2010-10-01"
    },
    {
      "vehicleId": 19428,
      "modelId": 5209,
      "manufacturerName": "OPEL",
      "modelName": "ASTRA H GTC (A04)",
      "typeEngineName": "1.8 (L08)",
      "constructionIntervalStart": "2006-01-01",
      "constructionIntervalEnd": "2010-10-01"
    },
    {
      "vehicleId": 22677,
      "modelId": 5453,
      "manufacturerName": "OPEL",
      "modelName": "ASTRA H TwinTop (A04)",
      "typeEngineName": "1.6 Turbo (L67)",
      "constructionIntervalStart": "2007-02-01",
      "constructionIntervalEnd": "2010-10-01"
    },
    {
      "vehicleId": 23239,
      "modelId": 4872,
      "manufacturerName": "VAUXHALL",
      "modelName": "VECTRA Mk II (C) (Z02)",
      "typeEngineName": "1.8",
      "constructionIntervalStart": "2006-01-01",
      "constructionIntervalEnd": "2008-07-01"
    },
    {
      "vehicleId": 23251,
      "modelId": 4873,
      "manufacturerName": "VAUXHALL",
      "modelName": "VECTRA Mk II (C) GTS (Z02)",
      "typeEngineName": "1.8",
      "constructionIntervalStart": "2006-01-01",
      "constructionIntervalEnd": "2008-07-01"
    },
    {
      "vehicleId": 23258,
      "modelId": 5152,
      "manufacturerName": "VAUXHALL",
      "modelName": "VECTRA Mk II (C) Estate (Z02)",
      "typeEngineName": "1.8",
      "constructionIntervalStart": "2006-01-01",
      "constructionIntervalEnd": "2008-07-01"
    },
    {
      "vehicleId": 23272,
      "modelId": 6413,
      "manufacturerName": "VAUXHALL",
      "modelName": "CORSA Mk III (D) (S07)",
      "typeEngineName": "1.6 VXR (L08)",
      "constructionIntervalStart": "2006-11-01",
      "constructionIntervalEnd": "2014-08-01"
    },
    {
      "vehicleId": 23356,
      "modelId": 5452,
      "manufacturerName": "ALFA ROMEO",
      "modelName": "159 (939_)",
      "typeEngineName": "1.8 MPI (939AXL1A)",
      "constructionIntervalStart": "2005-06-01",
      "constructionIntervalEnd": "2011-11-01"
    },
    {
      "vehicleId": 23497,
      "modelId": 5598,
      "manufacturerName": "OPEL",
      "modelName": "CORSA D (S07)",
      "typeEngineName": "1.6 Turbo (L08, L68)",
      "constructionIntervalStart": "2007-05-01",
      "constructionIntervalEnd": "2014-08-01"
    },
    {
      "vehicleId": 25501,
      "modelId": 5425,
      "manufacturerName": "OPEL",
      "modelName": "ZAFIRA / ZAFIRA FAMILY B (A05)",
      "typeEngineName": "1.6 (M75)",
      "constructionIntervalStart": "2008-01-01",
      "constructionIntervalEnd": "2015-04-01"
    },
    {
      "vehicleId": 27609,
      "modelId": 5518,
      "manufacturerName": "VAUXHALL",
      "modelName": "ZAFIRA Mk II (B) (A05)",
      "typeEngineName": "1.6",
      "constructionIntervalStart": "2007-12-01",
      "constructionIntervalEnd": "2014-11-01"
    },
    {
      "vehicleId": 28001,
      "modelId": 5006,
      "manufacturerName": "VAUXHALL",
      "modelName": "SIGNUM (Z03)",
      "typeEngineName": "1.8",
      "constructionIntervalStart": "2005-08-01",
      "constructionIntervalEnd": "2008-05-01"
    },
    {
      "vehicleId": 28214,
      "modelId": 7581,
      "manufacturerName": "OPEL",
      "modelName": "INSIGNIA A (G09)",
      "typeEngineName": "1.6 (68)",
      "constructionIntervalStart": "2008-07-01",
      "constructionIntervalEnd": "2017-03-01"
    },
    {
      "vehicleId": 28221,
      "modelId": 7582,
      "manufacturerName": "OPEL",
      "modelName": "INSIGNIA A Saloon (G09)",
      "typeEngineName": "1.6 (69)",
      "constructionIntervalStart": "2008-07-01",
      "constructionIntervalEnd": "2017-03-01"
    },
    {
      "vehicleId": 28610,
      "modelId": 7599,
      "manufacturerName": "VAUXHALL",
      "modelName": "INSIGNIA Mk I (A) Saloon (G09)",
      "typeEngineName": "1.8 (69)",
      "constructionIntervalStart": "2008-07-01",
      "constructionIntervalEnd": "2017-05-01"
    },
    {
      "vehicleId": 29923,
      "modelId": 7861,
      "manufacturerName": "OPEL",
      "modelName": "INSIGNIA A Sports Tourer (G09)",
      "typeEngineName": "1.6 (35)",
      "constructionIntervalStart": "2008-07-01",
      "constructionIntervalEnd": "2012-06-01"
    },
    {
      "vehicleId": 29938,
      "modelId": 7863,
      "manufacturerName": "VAUXHALL",
      "modelName": "INSIGNIA Mk I (A) Sports Tourer (G09)",
      "typeEngineName": "1.8 (35)",
      "constructionIntervalStart": "2008-07-01",
      "constructionIntervalEnd": "2017-05-01"
    },
    {
      "vehicleId": 30765,
      "modelId": 5425,
      "manufacturerName": "OPEL",
      "modelName": "ZAFIRA / ZAFIRA FAMILY B (A05)",
      "typeEngineName": "1.6 CNG Turbo (M75)",
      "constructionIntervalStart": "2010-04-01",
      "constructionIntervalEnd": "2015-04-01"
    },
    {
      "vehicleId": 30933,
      "modelId": 7918,
      "manufacturerName": "OPEL",
      "modelName": "ASTRA H Saloon (A04)",
      "typeEngineName": "1.8 (L69)",
      "constructionIntervalStart": "2007-02-01",
      "constructionIntervalEnd": "2012-09-01"
    },
    {
      "vehicleId": 30962,
      "modelId": 7582,
      "manufacturerName": "OPEL",
      "modelName": "INSIGNIA A Saloon (G09)",
      "typeEngineName": "1.6 Turbo (69)",
      "constructionIntervalStart": "2008-07-01",
      "constructionIntervalEnd": "2017-03-01"
    },
    {
      "vehicleId": 30963,
      "modelId": 7861,
      "manufacturerName": "OPEL",
      "modelName": "INSIGNIA A Sports Tourer (G09)",
      "typeEngineName": "1.6 Turbo (35)",
      "constructionIntervalStart": "2009-01-01",
      "constructionIntervalEnd": "2013-06-01"
    },
    {
      "vehicleId": 30964,
      "modelId": 7862,
      "manufacturerName": "VAUXHALL",
      "modelName": "INSIGNIA Mk I (A) Hatchback (G09)",
      "typeEngineName": "1.6 Turbo (68)",
      "constructionIntervalStart": "2009-01-01",
      "constructionIntervalEnd": "2017-05-01"
    },
    {
      "vehicleId": 30965,
      "modelId": 7599,
      "manufacturerName": "VAUXHALL",
      "modelName": "INSIGNIA Mk I (A) Saloon (G09)",
      "typeEngineName": "1.6 Turbo (69)",
      "constructionIntervalStart": "2009-01-01",
      "constructionIntervalEnd": "2017-05-01"
    },
    {
      "vehicleId": 30966,
      "modelId": 7863,
      "manufacturerName": "VAUXHALL",
      "modelName": "INSIGNIA Mk I (A) Sports Tourer (G09)",
      "typeEngineName": "1.6 Turbo (35)",
      "constructionIntervalStart": "2009-01-01",
      "constructionIntervalEnd": "2017-05-01"
    },
    {
      "vehicleId": 31120,
      "modelId": 7581,
      "manufacturerName": "OPEL",
      "modelName": "INSIGNIA A (G09)",
      "typeEngineName": "1.6 Turbo (68)",
      "constructionIntervalStart": "2008-07-01",
      "constructionIntervalEnd": "2017-03-01"
    },
    {
      "vehicleId": 31969,
      "modelId": 5598,
      "manufacturerName": "OPEL",
      "modelName": "CORSA D (S07)",
      "typeEngineName": "1.4 (L08, L68)",
      "constructionIntervalStart": "2009-09-01",
      "constructionIntervalEnd": "2014-08-01"
    },
    {
      "vehicleId": 31977,
      "modelId": 5531,
      "manufacturerName": "VAUXHALL",
      "modelName": "ASTRA Mk V (H) Sport Hatch (A04)",
      "typeEngineName": "1.8 i 16V (L08)",
      "constructionIntervalStart": "2007-03-01",
      "constructionIntervalEnd": "2010-11-01"
    },
    {
      "vehicleId": 32085,
      "modelId": 8261,
      "manufacturerName": "OPEL",
      "modelName": "ASTRA J (P10)",
      "typeEngineName": "1.4 (68)",
      "constructionIntervalStart": "2009-12-01",
      "constructionIntervalEnd": "2015-10-01"
    },
    {
      "vehicleId": 32086,
      "modelId": 8261,
      "manufacturerName": "OPEL",
      "modelName": "ASTRA J (P10)",
      "typeEngineName": "1.4 (68)",
      "constructionIntervalStart": "2009-12-01",
      "constructionIntervalEnd": "2015-10-01"
    },
    {
      "vehicleId": 32087,
      "modelId": 8261,
      "manufacturerName": "OPEL",
      "modelName": "ASTRA J (P10)",
      "typeEngineName": "1.6 (68)",
      "constructionIntervalStart": "2009-12-01",
      "constructionIntervalEnd": "2015-10-01"
    },
    {
      "vehicleId": 32088,
      "modelId": 8261,
      "manufacturerName": "OPEL",
      "modelName": "ASTRA J (P10)",
      "typeEngineName": "1.4 Turbo (68)",
      "constructionIntervalStart": "2009-12-01",
      "constructionIntervalEnd": "2015-10-01"
    },
    {
      "vehicleId": 32089,
      "modelId": 8261,
      "manufacturerName": "OPEL",
      "modelName": "ASTRA J (P10)",
      "typeEngineName": "1.6 Turbo (68)",
      "constructionIntervalStart": "2009-12-01",
      "constructionIntervalEnd": "2015-10-01"
    },
    {
      "vehicleId": 32146,
      "modelId": 8301,
      "manufacturerName": "VAUXHALL",
      "modelName": "ASTRA Mk VI (J) (P10)",
      "typeEngineName": "1.6",
      "constructionIntervalStart": "2009-12-01",
      "constructionIntervalEnd": "2015-10-01"
    },
    {
      "vehicleId": 32147,
      "modelId": 8301,
      "manufacturerName": "VAUXHALL",
      "modelName": "ASTRA Mk VI (J) (P10)",
      "typeEngineName": "1.4",
      "constructionIntervalStart": "2009-12-01",
      "constructionIntervalEnd": "2015-10-01"
    },
    {
      "vehicleId": 32148,
      "modelId": 8301,
      "manufacturerName": "VAUXHALL",
      "modelName": "ASTRA Mk VI (J) (P10)",
      "typeEngineName": "1.4",
      "constructionIntervalStart": "2009-12-01",
      "constructionIntervalEnd": "2015-10-01"
    },
    {
      "vehicleId": 32153,
      "modelId": 8301,
      "manufacturerName": "VAUXHALL",
      "modelName": "ASTRA Mk VI (J) (P10)",
      "typeEngineName": "1.6 Turbo",
      "constructionIntervalStart": "2009-12-01",
      "constructionIntervalEnd": "2015-10-01"
    },
    {
      "vehicleId": 33059,
      "modelId": 8549,
      "manufacturerName": "OPEL",
      "modelName": "MERIVA B MPV (S10)",
      "typeEngineName": "1.4 (75)",
      "constructionIntervalStart": "2010-06-01",
      "constructionIntervalEnd": "2017-03-01"
    },
    {
      "vehicleId": 33061,
      "modelId": 8549,
      "manufacturerName": "OPEL",
      "modelName": "MERIVA B MPV (S10)",
      "typeEngineName": "1.4 (75)",
      "constructionIntervalStart": "2010-06-01",
      "constructionIntervalEnd": "2017-03-01"
    },
    {
      "vehicleId": 33226,
      "modelId": 8715,
      "manufacturerName": "CHEVROLET (SGM)",
      "modelName": "EPICA (SEV, CEV)",
      "typeEngineName": "1.8",
      "constructionIntervalStart": "2009-10-01",
      "constructionIntervalEnd": "2015-12-01"
    },
    {
      "vehicleId": 33498,
      "modelId": 8645,
      "manufacturerName": "SAAB",
      "modelName": "9-5 (YS3G)",
      "typeEngineName": "1.6 Turbo",
      "constructionIntervalStart": "2010-05-01",
      "constructionIntervalEnd": "2012-01-01"
    },
    {
      "vehicleId": 33723,
      "modelId": 5598,
      "manufacturerName": "OPEL",
      "modelName": "CORSA D (S07)",
      "typeEngineName": "1.2 (L08, L68)",
      "constructionIntervalStart": "2009-12-01",
      "constructionIntervalEnd": "2014-08-01"
    },
    {
      "vehicleId": 33724,
      "modelId": 5598,
      "manufacturerName": "OPEL",
      "modelName": "CORSA D (S07)",
      "typeEngineName": "1.2 (L08, L68)",
      "constructionIntervalStart": "2009-12-01",
      "constructionIntervalEnd": "2014-08-01"
    },
    {
      "vehicleId": 33725,
      "modelId": 5598,
      "manufacturerName": "OPEL",
      "modelName": "CORSA D (S07)",
      "typeEngineName": "1.4 (L08, L68)",
      "constructionIntervalStart": "2009-12-01",
      "constructionIntervalEnd": "2014-08-01"
    },
    {
      "vehicleId": 33729,
      "modelId": 6413,
      "manufacturerName": "VAUXHALL",
      "modelName": "CORSA Mk III (D) (S07)",
      "typeEngineName": "1.4 (L08)",
      "constructionIntervalStart": "2010-01-01",
      "constructionIntervalEnd": "2014-08-01"
    },
    {
      "vehicleId": 33731,
      "modelId": 8754,
      "manufacturerName": "VAUXHALL",
      "modelName": "MERIVA Mk II (B) (S10)",
      "typeEngineName": "1.4",
      "constructionIntervalStart": "2010-06-01",
      "constructionIntervalEnd": "2017-03-01"
    },
    {
      "vehicleId": 33732,
      "modelId": 8754,
      "manufacturerName": "VAUXHALL",
      "modelName": "MERIVA Mk II (B) (S10)",
      "typeEngineName": "1.4",
      "constructionIntervalStart": "2010-06-01",
      "constructionIntervalEnd": "2013-10-01"
    },
    {
      "vehicleId": 33735,
      "modelId": 8754,
      "manufacturerName": "VAUXHALL",
      "modelName": "MERIVA Mk II (B) (S10)",
      "typeEngineName": "1.4",
      "constructionIntervalStart": "2010-06-01",
      "constructionIntervalEnd": "2013-10-01"
    },
    {
      "vehicleId": 33760,
      "modelId": 6413,
      "manufacturerName": "VAUXHALL",
      "modelName": "CORSA Mk III (D) (S07)",
      "typeEngineName": "1.0 i 12V (L08)",
      "constructionIntervalStart": "2010-01-01",
      "constructionIntervalEnd": "2014-08-01"
    },
    {
      "vehicleId": 33761,
      "modelId": 6413,
      "manufacturerName": "VAUXHALL",
      "modelName": "CORSA Mk III (D) (S07)",
      "typeEngineName": "1.2 i 16V (L08)",
      "constructionIntervalStart": "2009-12-01",
      "constructionIntervalEnd": "2014-08-01"
    },
    {
      "vehicleId": 53382,
      "modelId": 5425,
      "manufacturerName": "OPEL",
      "modelName": "ZAFIRA / ZAFIRA FAMILY B (A05)",
      "typeEngineName": "1.8 (M75)",
      "constructionIntervalStart": "2013-06-01",
      "constructionIntervalEnd": "2015-04-01"
    },
    {
      "vehicleId": 54975,
      "modelId": 6413,
      "manufacturerName": "VAUXHALL",
      "modelName": "CORSA Mk III (D) (S07)",
      "typeEngineName": "1.2 LPG (L08)",
      "constructionIntervalStart": "2011-08-01",
      "constructionIntervalEnd": "2014-08-01"
    },
    {
      "vehicleId": 54976,
      "modelId": 6413,
      "manufacturerName": "VAUXHALL",
      "modelName": "CORSA Mk III (D) (S07)",
      "typeEngineName": "1.2 (L08)",
      "constructionIntervalStart": "2010-06-01",
      "constructionIntervalEnd": "2014-08-01"
    },
    {
      "vehicleId": 56428,
      "modelId": 7863,
      "manufacturerName": "VAUXHALL",
      "modelName": "INSIGNIA Mk I (A) Sports Tourer (G09)",
      "typeEngineName": "1.4 LPG (35)",
      "constructionIntervalStart": "2012-07-01",
      "constructionIntervalEnd": "2017-05-01"
    },
    {
      "vehicleId": 56429,
      "modelId": 7599,
      "manufacturerName": "VAUXHALL",
      "modelName": "INSIGNIA Mk I (A) Saloon (G09)",
      "typeEngineName": "1.4 LPG (69)",
      "constructionIntervalStart": "2012-07-01",
      "constructionIntervalEnd": "2017-05-01"
    },
    {
      "vehicleId": 56430,
      "modelId": 7862,
      "manufacturerName": "VAUXHALL",
      "modelName": "INSIGNIA Mk I (A) Hatchback (G09)",
      "typeEngineName": "1.4 LPG (68)",
      "constructionIntervalStart": "2012-07-01",
      "constructionIntervalEnd": "2017-05-01"
    },
    {
      "vehicleId": 56787,
      "modelId": 7581,
      "manufacturerName": "OPEL",
      "modelName": "INSIGNIA A (G09)",
      "typeEngineName": "1.4 LPG (68)",
      "constructionIntervalStart": "2012-07-01",
      "constructionIntervalEnd": "2017-03-01"
    },
    {
      "vehicleId": 56788,
      "modelId": 7582,
      "manufacturerName": "OPEL",
      "modelName": "INSIGNIA A Saloon (G09)",
      "typeEngineName": "1.4 LPG (69)",
      "constructionIntervalStart": "2012-07-01",
      "constructionIntervalEnd": "2017-03-01"
    },
    {
      "vehicleId": 56789,
      "modelId": 5598,
      "manufacturerName": "OPEL",
      "modelName": "CORSA D (S07)",
      "typeEngineName": "1.4 (L08, L68)",
      "constructionIntervalStart": "2012-07-01",
      "constructionIntervalEnd": "2014-08-01"
    },
    {
      "vehicleId": 56861,
      "modelId": 6413,
      "manufacturerName": "VAUXHALL",
      "modelName": "CORSA Mk III (D) (S07)",
      "typeEngineName": "1.4 (L08)",
      "constructionIntervalStart": "2012-08-01",
      "constructionIntervalEnd": "2014-08-01"
    },
    {
      "vehicleId": 58707,
      "modelId": 11177,
      "manufacturerName": "OPEL",
      "modelName": "CASCADA (W13)",
      "typeEngineName": "1.4 (67)",
      "constructionIntervalStart": "2013-04-01",
      "constructionIntervalEnd": "2018-04-01"
    },
    {
      "vehicleId": 58708,
      "modelId": 11177,
      "manufacturerName": "OPEL",
      "modelName": "CASCADA (W13)",
      "typeEngineName": "1.4 Turbo (67)",
      "constructionIntervalStart": "2013-03-01",
      "constructionIntervalEnd": "2018-04-01"
    },
    {
      "vehicleId": 106472,
      "modelId": 5518,
      "manufacturerName": "VAUXHALL",
      "modelName": "ZAFIRA Mk II (B) (A05)",
      "typeEngineName": "1.8",
      "constructionIntervalStart": "2013-04-01",
      "constructionIntervalEnd": "2014-11-01"
    },
    {
      "vehicleId": 107797,
      "modelId": 13137,
      "manufacturerName": "OPEL",
      "modelName": "CORSA E (X15)",
      "typeEngineName": "1.4 Turbo (08, 68)",
      "constructionIntervalStart": "2014-09-01",
      "constructionIntervalEnd": "2019-06-01"
    },
    {
      "vehicleId": 109279,
      "modelId": 10731,
      "manufacturerName": "OPEL",
      "modelName": "ADAM (M13)",
      "typeEngineName": "1.4 S",
      "constructionIntervalStart": "2014-11-01",
      "constructionIntervalEnd": "2019-01-01"
    },
    {
      "vehicleId": 109361,
      "modelId": 10640,
      "manufacturerName": "VAUXHALL",
      "modelName": "ADAM (M13)",
      "typeEngineName": "1.4 S",
      "constructionIntervalStart": "2014-11-01",
      "constructionIntervalEnd": "2019-01-01"
    },
    {
      "vehicleId": 118688,
      "modelId": 5598,
      "manufacturerName": "OPEL",
      "modelName": "CORSA D (S07)",
      "typeEngineName": "1.2 LPG (L08, L68)",
      "constructionIntervalStart": "2009-09-01",
      "constructionIntervalEnd": "2011-12-01"
    },
    {
      "vehicleId": 125949,
      "modelId": 9017,
      "manufacturerName": "OPEL",
      "modelName": "ASTRA J Sports Tourer (P10)",
      "typeEngineName": "1.4 (35)",
      "constructionIntervalStart": "2010-10-01",
      "constructionIntervalEnd": "2015-10-01"
    },
    {
      "vehicleId": 126265,
      "modelId": 9036,
      "manufacturerName": "VAUXHALL",
      "modelName": "ASTRA Mk VI (J) Estate (P10)",
      "typeEngineName": "1.4",
      "constructionIntervalStart": "2010-10-01",
      "constructionIntervalEnd": "2015-10-01"
    },
    {
      "vehicleId": 126646,
      "modelId": 8261,
      "manufacturerName": "OPEL",
      "modelName": "ASTRA J (P10)",
      "typeEngineName": "1.6 Turbo 4x4 (68)",
      "constructionIntervalStart": "2009-12-01",
      "constructionIntervalEnd": "2015-10-01"
    },
    {
      "vehicleId": 129092,
      "modelId": 37099,
      "manufacturerName": "OPEL",
      "modelName": "ASTRA H CLASSIC Saloon (A04)",
      "typeEngineName": "1.8 (L69)",
      "constructionIntervalStart": "2007-02-01",
      "constructionIntervalEnd": "2012-09-01"
    },
    {
      "vehicleId": 129655,
      "modelId": 7862,
      "manufacturerName": "VAUXHALL",
      "modelName": "INSIGNIA Mk I (A) Hatchback (G09)",
      "typeEngineName": "1.6",
      "constructionIntervalStart": "2008-07-01",
      "constructionIntervalEnd": "2012-07-01"
    },
    {
      "vehicleId": 129656,
      "modelId": 7599,
      "manufacturerName": "VAUXHALL",
      "modelName": "INSIGNIA Mk I (A) Saloon (G09)",
      "typeEngineName": "1.6",
      "constructionIntervalStart": "2008-07-01",
      "constructionIntervalEnd": "2012-07-01"
    },
    {
      "vehicleId": 129657,
      "modelId": 7863,
      "manufacturerName": "VAUXHALL",
      "modelName": "INSIGNIA Mk I (A) Sports Tourer (G09)",
      "typeEngineName": "1.6",
      "constructionIntervalStart": "2008-07-01",
      "constructionIntervalEnd": "2012-07-01"
    },
    {
      "vehicleId": 132555,
      "modelId": 10351,
      "manufacturerName": "OPEL",
      "modelName": "ASTRA J Saloon",
      "typeEngineName": "1.4",
      "constructionIntervalStart": "2014-01-01",
      "constructionIntervalEnd": "2015-10-01"
    },
    {
      "vehicleId": 132592,
      "modelId": 5425,
      "manufacturerName": "OPEL",
      "modelName": "ZAFIRA / ZAFIRA FAMILY B (A05)",
      "typeEngineName": "1.6 FlexFuel (M75)",
      "constructionIntervalStart": "2008-08-01",
      "constructionIntervalEnd": "2012-12-01"
    },
    {
      "vehicleId": 132798,
      "modelId": 9180,
      "manufacturerName": "OPEL",
      "modelName": "CORSA D Hatchback Van (S07)",
      "typeEngineName": "1.4 (L08)",
      "constructionIntervalStart": "2012-07-01",
      "constructionIntervalEnd": "2014-08-01"
    },
    {
      "vehicleId": 132799,
      "modelId": 9180,
      "manufacturerName": "OPEL",
      "modelName": "CORSA D Hatchback Van (S07)",
      "typeEngineName": "1.4 (L08)",
      "constructionIntervalStart": "2012-07-01",
      "constructionIntervalEnd": "2014-08-01"
    },
    {
      "vehicleId": 143156,
      "modelId": 41716,
      "manufacturerName": "OPEL",
      "modelName": "MERIVA B VAN (S10)",
      "typeEngineName": "1.4 ECOTEC (75)",
      "constructionIntervalStart": "2013-01-01",
      "constructionIntervalEnd": "2017-03-01"
    },
    {
      "vehicleId": 5519,
      "modelId": 4926,
      "manufacturerName": "OPEL",
      "modelName": "MERIVA A MPV (X03)",
      "typeEngineName": "1.4 16V Twinport LPG (E75)",
      "constructionIntervalStart": "2004-07-01",
      "constructionIntervalEnd": "2010-05-01"
    },
    {
      "vehicleId": 18228,
      "modelId": 4926,
      "manufacturerName": "OPEL",
      "modelName": "MERIVA A MPV (X03)",
      "typeEngineName": "1.4 16V Twinport (E75)",
      "constructionIntervalStart": "2004-07-01",
      "constructionIntervalEnd": "2010-05-01"
    },
    {
      "vehicleId": 5573,
      "modelId": 5145,
      "manufacturerName": "OPEL",
      "modelName": "ASTRA H Estate (A04)",
      "typeEngineName": "1.6 LPG (L35)",
      "constructionIntervalStart": "2009-08-01",
      "constructionIntervalEnd": "2010-10-01"
    },
    {
      "vehicleId": 19933,
      "modelId": 4926,
      "manufacturerName": "OPEL",
      "modelName": "MERIVA A MPV (X03)",
      "typeEngineName": "1.6 Turbo (E75)",
      "constructionIntervalStart": "2005-09-01",
      "constructionIntervalEnd": "2010-05-01"
    },
    {
      "vehicleId": 20000,
      "modelId": 5008,
      "manufacturerName": "VAUXHALL",
      "modelName": "MERIVA A (X03)",
      "typeEngineName": "1.6 Turbo",
      "constructionIntervalStart": "2006-05-01",
      "constructionIntervalEnd": "2010-06-01"
    },
    {
      "vehicleId": 28842,
      "modelId": 5475,
      "manufacturerName": "VAUXHALL",
      "modelName": "ASTRA Mk V (H) Estate (A04)",
      "typeEngineName": "1.6 (L35)",
      "constructionIntervalStart": "2004-08-01",
      "constructionIntervalEnd": "2011-03-01"
    },
    {
      "vehicleId": 30474,
      "modelId": 7918,
      "manufacturerName": "OPEL",
      "modelName": "ASTRA H Saloon (A04)",
      "typeEngineName": "1.6 (L69)",
      "constructionIntervalStart": "2007-02-01",
      "constructionIntervalEnd": "2014-05-01"
    },
    {
      "vehicleId": 122662,
      "modelId": 37067,
      "manufacturerName": "OPEL",
      "modelName": "ASTRA H CLASSIC Hatchback (A04)",
      "typeEngineName": "1.6 (L48)",
      "constructionIntervalStart": "2009-01-01",
      "constructionIntervalEnd": null
    },
    {
      "vehicleId": 123046,
      "modelId": 37099,
      "manufacturerName": "OPEL",
      "modelName": "ASTRA H CLASSIC Saloon (A04)",
      "typeEngineName": "1.6 (L69)",
      "constructionIntervalStart": "2009-01-01",
      "constructionIntervalEnd": "2014-05-01"
    },
    {
      "vehicleId": 27004,
      "modelId": 9591,
      "manufacturerName": "CHEVROLET",
      "modelName": "AVEO Hatchback (T300)",
      "typeEngineName": "1.4 Turbo",
      "constructionIntervalStart": "2013-08-01",
      "constructionIntervalEnd": null
    },
    {
      "vehicleId": 55444,
      "modelId": 8127,
      "manufacturerName": "CHEVROLET",
      "modelName": "CRUZE (J300)",
      "typeEngineName": "1.8 LPG",
      "constructionIntervalStart": "2011-06-01",
      "constructionIntervalEnd": null
    },
    {
      "vehicleId": 56753,
      "modelId": 9625,
      "manufacturerName": "CHEVROLET",
      "modelName": "CRUZE Hatchback (J305)",
      "typeEngineName": "1.4",
      "constructionIntervalStart": "2012-06-01",
      "constructionIntervalEnd": null
    },
    {
      "vehicleId": 6044,
      "modelId": 5145,
      "manufacturerName": "OPEL",
      "modelName": "ASTRA H Estate (A04)",
      "typeEngineName": "1.4 LPG (L35)",
      "constructionIntervalStart": "2009-08-01",
      "constructionIntervalEnd": "2010-10-01"
    },
    {
      "vehicleId": 9949,
      "modelId": 5098,
      "manufacturerName": "OPEL",
      "modelName": "ASTRA H (A04)",
      "typeEngineName": "1.4 LPG (L48)",
      "constructionIntervalStart": "2009-08-01",
      "constructionIntervalEnd": "2010-10-01"
    },
    {
      "vehicleId": 17844,
      "modelId": 5098,
      "manufacturerName": "OPEL",
      "modelName": "ASTRA H (A04)",
      "typeEngineName": "1.4 (L48)",
      "constructionIntervalStart": "2004-03-01",
      "constructionIntervalEnd": "2010-10-01"
    },
    {
      "vehicleId": 18073,
      "modelId": 5145,
      "manufacturerName": "OPEL",
      "modelName": "ASTRA H Estate (A04)",
      "typeEngineName": "1.4 (L35)",
      "constructionIntervalStart": "2004-08-01",
      "constructionIntervalEnd": "2010-10-01"
    },
    {
      "vehicleId": 20024,
      "modelId": 5008,
      "manufacturerName": "VAUXHALL",
      "modelName": "MERIVA A (X03)",
      "typeEngineName": "1.4 16V Twinport",
      "constructionIntervalStart": "2003-01-01",
      "constructionIntervalEnd": "2010-06-01"
    },
    {
      "vehicleId": 32812,
      "modelId": 7600,
      "manufacturerName": "VAUXHALL",
      "modelName": "ASTRAVAN Mk V (H) Estate Van (A04)",
      "typeEngineName": "1.4 i",
      "constructionIntervalStart": "2005-03-01",
      "constructionIntervalEnd": null
    },
    {
      "vehicleId": 33738,
      "modelId": 5531,
      "manufacturerName": "VAUXHALL",
      "modelName": "ASTRA Mk V (H) Sport Hatch (A04)",
      "typeEngineName": "1.4 i 16V (L08)",
      "constructionIntervalStart": "2005-03-01",
      "constructionIntervalEnd": "2010-11-01"
    },
    {
      "vehicleId": 129088,
      "modelId": 37112,
      "manufacturerName": "OPEL",
      "modelName": "ASTRA H CLASSIC Estate (A04)",
      "typeEngineName": "1.4 (L35)",
      "constructionIntervalStart": "2009-01-01",
      "constructionIntervalEnd": null
    },
    {
      "vehicleId": 129091,
      "modelId": 37067,
      "manufacturerName": "OPEL",
      "modelName": "ASTRA H CLASSIC Hatchback (A04)",
      "typeEngineName": "1.4 (L48)",
      "constructionIntervalStart": "2009-01-01",
      "constructionIntervalEnd": null
    },
    {
      "vehicleId": 132595,
      "modelId": 7918,
      "manufacturerName": "OPEL",
      "modelName": "ASTRA H Saloon (A04)",
      "typeEngineName": "1.4 (L69)",
      "constructionIntervalStart": "2007-02-01",
      "constructionIntervalEnd": "2010-06-01"
    },
    {
      "vehicleId": 132756,
      "modelId": 9183,
      "manufacturerName": "OPEL",
      "modelName": "ASTRA H Estate Van (L70)",
      "typeEngineName": "1.4 EcoTec (L70)",
      "constructionIntervalStart": "2004-12-01",
      "constructionIntervalEnd": "2012-12-01"
    },
    {
      "vehicleId": 7212,
      "modelId": 4658,
      "manufacturerName": "VAUXHALL",
      "modelName": "CORSA Mk II (C) (X01)",
      "typeEngineName": "1.4 Twinport (F08, F68)",
      "constructionIntervalStart": "2003-06-01",
      "constructionIntervalEnd": "2006-10-01"
    },
    {
      "vehicleId": 7749,
      "modelId": 10264,
      "manufacturerName": "OPEL",
      "modelName": "MOKKA / MOKKA X (J13)",
      "typeEngineName": "1.8 4x4 (_76)",
      "constructionIntervalStart": "2013-01-01",
      "constructionIntervalEnd": "2019-12-01"
    },
    {
      "vehicleId": 7806,
      "modelId": 10264,
      "manufacturerName": "OPEL",
      "modelName": "MOKKA / MOKKA X (J13)",
      "typeEngineName": "1.8 (_76)",
      "constructionIntervalStart": "2013-01-01",
      "constructionIntervalEnd": "2019-12-01"
    },
    {
      "vehicleId": 20740,
      "modelId": 10264,
      "manufacturerName": "OPEL",
      "modelName": "MOKKA / MOKKA X (J13)",
      "typeEngineName": "1.4 (_76)",
      "constructionIntervalStart": "2013-04-01",
      "constructionIntervalEnd": "2019-12-01"
    },
    {
      "vehicleId": 105763,
      "modelId": 10325,
      "manufacturerName": "VAUXHALL",
      "modelName": "MOKKA / MOKKA X (J13)",
      "typeEngineName": "1.4",
      "constructionIntervalStart": "2013-04-01",
      "constructionIntervalEnd": "2019-12-01"
    },
    {
      "vehicleId": 131549,
      "modelId": 10264,
      "manufacturerName": "OPEL",
      "modelName": "MOKKA / MOKKA X (J13)",
      "typeEngineName": "1.4 (_76)",
      "constructionIntervalStart": "2018-06-01",
      "constructionIntervalEnd": "2019-12-01"
    },
    {
      "vehicleId": 8711,
      "modelId": 8127,
      "manufacturerName": "CHEVROLET",
      "modelName": "CRUZE (J300)",
      "typeEngineName": "1.6",
      "constructionIntervalStart": "2009-05-01",
      "constructionIntervalEnd": null
    },
    {
      "vehicleId": 9176,
      "modelId": 9180,
      "manufacturerName": "OPEL",
      "modelName": "CORSA D Hatchback Van (S07)",
      "typeEngineName": "1.0 (L08)",
      "constructionIntervalStart": "2006-08-01",
      "constructionIntervalEnd": "2014-08-01"
    },
    {
      "vehicleId": 9177,
      "modelId": 9180,
      "manufacturerName": "OPEL",
      "modelName": "CORSA D Hatchback Van (S07)",
      "typeEngineName": "1.2 (L08)",
      "constructionIntervalStart": "2006-08-01",
      "constructionIntervalEnd": "2014-08-01"
    },
    {
      "vehicleId": 19723,
      "modelId": 5598,
      "manufacturerName": "OPEL",
      "modelName": "CORSA D (S07)",
      "typeEngineName": "1.2 (L08, L68)",
      "constructionIntervalStart": "2006-07-01",
      "constructionIntervalEnd": "2014-08-01"
    },
    {
      "vehicleId": 9252,
      "modelId": 9184,
      "manufacturerName": "OPEL",
      "modelName": "ZAFIRA B Box Body/MPV (A05)",
      "typeEngineName": "1.6 CNG Turbo VAN (M75)",
      "constructionIntervalStart": "2009-02-01",
      "constructionIntervalEnd": "2015-04-01"
    },
    {
      "vehicleId": 9265,
      "modelId": 5598,
      "manufacturerName": "OPEL",
      "modelName": "CORSA D (S07)",
      "typeEngineName": "1.4 LPG (L08, L68)",
      "constructionIntervalStart": "2009-09-01",
      "constructionIntervalEnd": "2014-08-01"
    },
    {
      "vehicleId": 9948,
      "modelId": 5209,
      "manufacturerName": "OPEL",
      "modelName": "ASTRA H GTC (A04)",
      "typeEngineName": "1.4 (L08)",
      "constructionIntervalStart": "2005-03-01",
      "constructionIntervalEnd": "2010-10-01"
    },
    {
      "vehicleId": 9997,
      "modelId": 9591,
      "manufacturerName": "CHEVROLET",
      "modelName": "AVEO Hatchback (T300)",
      "typeEngineName": "1.2",
      "constructionIntervalStart": "2011-03-01",
      "constructionIntervalEnd": null
    },
    {
      "vehicleId": 10572,
      "modelId": 9592,
      "manufacturerName": "CHEVROLET",
      "modelName": "AVEO Saloon (T300)",
      "typeEngineName": "1.2",
      "constructionIntervalStart": "2011-03-01",
      "constructionIntervalEnd": null
    },
    {
      "vehicleId": 55445,
      "modelId": 9083,
      "manufacturerName": "CHEVROLET",
      "modelName": "ORLANDO (J309)",
      "typeEngineName": "1.8 LPG",
      "constructionIntervalStart": "2011-06-01",
      "constructionIntervalEnd": "2015-12-01"
    },
    {
      "vehicleId": 56317,
      "modelId": 9592,
      "manufacturerName": "CHEVROLET",
      "modelName": "AVEO Saloon (T300)",
      "typeEngineName": "1.6",
      "constructionIntervalStart": "2011-06-01",
      "constructionIntervalEnd": null
    },
    {
      "vehicleId": 57117,
      "modelId": 10819,
      "manufacturerName": "CHEVROLET",
      "modelName": "TRAX",
      "typeEngineName": "1.4 AWD",
      "constructionIntervalStart": "2012-12-01",
      "constructionIntervalEnd": null
    },
    {
      "vehicleId": 57387,
      "modelId": 9591,
      "manufacturerName": "CHEVROLET",
      "modelName": "AVEO Hatchback (T300)",
      "typeEngineName": "1.2 LPG",
      "constructionIntervalStart": "2012-11-01",
      "constructionIntervalEnd": "2015-12-01"
    },
    {
      "vehicleId": 57388,
      "modelId": 9592,
      "manufacturerName": "CHEVROLET",
      "modelName": "AVEO Saloon (T300)",
      "typeEngineName": "1.2 LPG",
      "constructionIntervalStart": "2012-11-01",
      "constructionIntervalEnd": "2015-12-01"
    },
    {
      "vehicleId": 57419,
      "modelId": 10516,
      "manufacturerName": "CHEVROLET",
      "modelName": "CRUZE Station Wagon (J308)",
      "typeEngineName": "1.6",
      "constructionIntervalStart": "2012-12-01",
      "constructionIntervalEnd": "2015-12-01"
    },
    {
      "vehicleId": 58099,
      "modelId": 9591,
      "manufacturerName": "CHEVROLET",
      "modelName": "AVEO Hatchback (T300)",
      "typeEngineName": "1.6",
      "constructionIntervalStart": "2011-06-01",
      "constructionIntervalEnd": null
    },
    {
      "vehicleId": 134898,
      "modelId": 9592,
      "manufacturerName": "CHEVROLET",
      "modelName": "AVEO Saloon (T300)",
      "typeEngineName": "1.2",
      "constructionIntervalStart": "2019-01-01",
      "constructionIntervalEnd": null
    },
    {
      "vehicleId": 9998,
      "modelId": 9591,
      "manufacturerName": "CHEVROLET",
      "modelName": "AVEO Hatchback (T300)",
      "typeEngineName": "1.2",
      "constructionIntervalStart": "2011-03-01",
      "constructionIntervalEnd": null
    },
    {
      "vehicleId": 10029,
      "modelId": 9592,
      "manufacturerName": "CHEVROLET",
      "modelName": "AVEO Saloon (T300)",
      "typeEngineName": "1.2",
      "constructionIntervalStart": "2011-03-01",
      "constructionIntervalEnd": null
    },
    {
      "vehicleId": 10035,
      "modelId": 9591,
      "manufacturerName": "CHEVROLET",
      "modelName": "AVEO Hatchback (T300)",
      "typeEngineName": "1.6",
      "constructionIntervalStart": "2011-03-01",
      "constructionIntervalEnd": null
    },
    {
      "vehicleId": 10019,
      "modelId": 9591,
      "manufacturerName": "CHEVROLET",
      "modelName": "AVEO Hatchback (T300)",
      "typeEngineName": "1.4",
      "constructionIntervalStart": "2011-03-01",
      "constructionIntervalEnd": null
    },
    {
      "vehicleId": 10444,
      "modelId": 9592,
      "manufacturerName": "CHEVROLET",
      "modelName": "AVEO Saloon (T300)",
      "typeEngineName": "1.4",
      "constructionIntervalStart": "2011-07-01",
      "constructionIntervalEnd": null
    },
    {
      "vehicleId": 10351,
      "modelId": 9625,
      "manufacturerName": "CHEVROLET",
      "modelName": "CRUZE Hatchback (J305)",
      "typeEngineName": "1.8",
      "constructionIntervalStart": "2011-06-01",
      "constructionIntervalEnd": null
    },
    {
      "vehicleId": 10450,
      "modelId": 7581,
      "manufacturerName": "OPEL",
      "modelName": "INSIGNIA A (G09)",
      "typeEngineName": "1.4 (68)",
      "constructionIntervalStart": "2011-04-01",
      "constructionIntervalEnd": "2017-03-01"
    },
    {
      "vehicleId": 10451,
      "modelId": 7582,
      "manufacturerName": "OPEL",
      "modelName": "INSIGNIA A Saloon (G09)",
      "typeEngineName": "1.4 (69)",
      "constructionIntervalStart": "2011-04-01",
      "constructionIntervalEnd": "2017-03-01"
    },
    {
      "vehicleId": 11941,
      "modelId": 7862,
      "manufacturerName": "VAUXHALL",
      "modelName": "INSIGNIA Mk I (A) Hatchback (G09)",
      "typeEngineName": "1.4 (68)",
      "constructionIntervalStart": "2011-04-01",
      "constructionIntervalEnd": "2017-05-01"
    },
    {
      "vehicleId": 11943,
      "modelId": 7863,
      "manufacturerName": "VAUXHALL",
      "modelName": "INSIGNIA Mk I (A) Sports Tourer (G09)",
      "typeEngineName": "1.4 (35)",
      "constructionIntervalStart": "2011-04-01",
      "constructionIntervalEnd": "2017-05-01"
    },
    {
      "vehicleId": 12038,
      "modelId": 7861,
      "manufacturerName": "OPEL",
      "modelName": "INSIGNIA A Sports Tourer (G09)",
      "typeEngineName": "1.4 (35)",
      "constructionIntervalStart": "2011-04-01",
      "constructionIntervalEnd": "2017-03-01"
    },
    {
      "vehicleId": 10458,
      "modelId": 9628,
      "manufacturerName": "OPEL",
      "modelName": "ASTRA J GTC",
      "typeEngineName": "1.4 (08)",
      "constructionIntervalStart": "2011-10-01",
      "constructionIntervalEnd": "2018-04-01"
    },
    {
      "vehicleId": 11272,
      "modelId": 9709,
      "manufacturerName": "VAUXHALL",
      "modelName": "ASTRA Mk VI (J) GTC (P10)",
      "typeEngineName": "1.4",
      "constructionIntervalStart": "2011-10-01",
      "constructionIntervalEnd": "2018-10-01"
    },
    {
      "vehicleId": 11276,
      "modelId": 9709,
      "manufacturerName": "VAUXHALL",
      "modelName": "ASTRA Mk VI (J) GTC (P10)",
      "typeEngineName": "1.4",
      "constructionIntervalStart": "2011-10-01",
      "constructionIntervalEnd": "2018-04-01"
    },
    {
      "vehicleId": 13951,
      "modelId": 9628,
      "manufacturerName": "OPEL",
      "modelName": "ASTRA J GTC",
      "typeEngineName": "1.4 Turbo (08)",
      "constructionIntervalStart": "2011-10-01",
      "constructionIntervalEnd": "2018-04-01"
    },
    {
      "vehicleId": 57116,
      "modelId": 10819,
      "manufacturerName": "CHEVROLET",
      "modelName": "TRAX",
      "typeEngineName": "1.6",
      "constructionIntervalStart": "2012-12-01",
      "constructionIntervalEnd": null
    },
    {
      "vehicleId": 11237,
      "modelId": 4658,
      "manufacturerName": "VAUXHALL",
      "modelName": "CORSA Mk II (C) (X01)",
      "typeEngineName": "1.2 Twinport (F08, F68)",
      "constructionIntervalStart": "2004-07-01",
      "constructionIntervalEnd": "2006-10-01"
    },
    {
      "vehicleId": 129003,
      "modelId": 4815,
      "manufacturerName": "VAUXHALL",
      "modelName": "CORSAVAN Mk II (C) Hatchback Van (X01)",
      "typeEngineName": "1.2 16V (F08)",
      "constructionIntervalStart": "2004-07-01",
      "constructionIntervalEnd": "2006-11-01"
    },
    {
      "vehicleId": 11277,
      "modelId": 6413,
      "manufacturerName": "VAUXHALL",
      "modelName": "CORSA Mk III (D) (S07)",
      "typeEngineName": "1.6 VXR (L08)",
      "constructionIntervalStart": "2011-06-01",
      "constructionIntervalEnd": "2014-08-01"
    },
    {
      "vehicleId": 132694,
      "modelId": 6413,
      "manufacturerName": "VAUXHALL",
      "modelName": "CORSA Mk III (D) (S07)",
      "typeEngineName": "1.6 VXR (L08)",
      "constructionIntervalStart": "2011-06-01",
      "constructionIntervalEnd": "2012-03-01"
    },
    {
      "vehicleId": 132704,
      "modelId": 6413,
      "manufacturerName": "VAUXHALL",
      "modelName": "CORSA Mk III (D) (S07)",
      "typeEngineName": "1.6 VXR (L08)",
      "constructionIntervalStart": "2011-06-01",
      "constructionIntervalEnd": "2014-08-01"
    },
    {
      "vehicleId": 11306,
      "modelId": 8759,
      "manufacturerName": "VAUXHALL",
      "modelName": "CORSAVAN Mk III (D) Hatchback Van (S07)",
      "typeEngineName": "1.2",
      "constructionIntervalStart": "2009-07-01",
      "constructionIntervalEnd": null
    },
    {
      "vehicleId": 23270,
      "modelId": 6413,
      "manufacturerName": "VAUXHALL",
      "modelName": "CORSA Mk III (D) (S07)",
      "typeEngineName": "1.2 (L08)",
      "constructionIntervalStart": "2006-08-01",
      "constructionIntervalEnd": "2014-08-01"
    },
    {
      "vehicleId": 54977,
      "modelId": 6413,
      "manufacturerName": "VAUXHALL",
      "modelName": "CORSA Mk III (D) (S07)",
      "typeEngineName": "1.2 LPG (L08)",
      "constructionIntervalStart": "2009-09-01",
      "constructionIntervalEnd": "2014-08-01"
    },
    {
      "vehicleId": 11324,
      "modelId": 9717,
      "manufacturerName": "OPEL",
      "modelName": "ZAFIRA TOURER C (P12)",
      "typeEngineName": "1.4 (75)",
      "constructionIntervalStart": "2011-10-01",
      "constructionIntervalEnd": null
    },
    {
      "vehicleId": 11325,
      "modelId": 9717,
      "manufacturerName": "OPEL",
      "modelName": "ZAFIRA TOURER C (P12)",
      "typeEngineName": "1.4 (75)",
      "constructionIntervalStart": "2011-10-01",
      "constructionIntervalEnd": null
    },
    {
      "vehicleId": 11712,
      "modelId": 9717,
      "manufacturerName": "OPEL",
      "modelName": "ZAFIRA TOURER C (P12)",
      "typeEngineName": "1.6 CNG (75)",
      "constructionIntervalStart": "2011-10-01",
      "constructionIntervalEnd": null
    },
    {
      "vehicleId": 55443,
      "modelId": 9717,
      "manufacturerName": "OPEL",
      "modelName": "ZAFIRA TOURER C (P12)",
      "typeEngineName": "1.4 LPG (75)",
      "constructionIntervalStart": "2011-10-01",
      "constructionIntervalEnd": null
    },
    {
      "vehicleId": 11326,
      "modelId": 9717,
      "manufacturerName": "OPEL",
      "modelName": "ZAFIRA TOURER C (P12)",
      "typeEngineName": "1.8 (75)",
      "constructionIntervalStart": "2011-10-01",
      "constructionIntervalEnd": null
    },
    {
      "vehicleId": 11711,
      "modelId": 9717,
      "manufacturerName": "OPEL",
      "modelName": "ZAFIRA TOURER C (P12)",
      "typeEngineName": "1.8 (75)",
      "constructionIntervalStart": "2011-10-01",
      "constructionIntervalEnd": null
    },
    {
      "vehicleId": 107553,
      "modelId": 13083,
      "manufacturerName": "VAUXHALL",
      "modelName": "CORSA Mk IV (E) (X15)",
      "typeEngineName": "1.4",
      "constructionIntervalStart": "2014-08-01",
      "constructionIntervalEnd": null
    },
    {
      "vehicleId": 109543,
      "modelId": 13559,
      "manufacturerName": "VAUXHALL",
      "modelName": "CORSAVAN Mk IV (E) Hatchback Van (X15)",
      "typeEngineName": "1.2",
      "constructionIntervalStart": "2014-10-01",
      "constructionIntervalEnd": null
    },
    {
      "vehicleId": 110026,
      "modelId": 13635,
      "manufacturerName": "OPEL",
      "modelName": "CORSA E Hatchback Van (X15)",
      "typeEngineName": "1.2 (08)",
      "constructionIntervalStart": "2015-01-01",
      "constructionIntervalEnd": null
    },
    {
      "vehicleId": 111856,
      "modelId": 13083,
      "manufacturerName": "VAUXHALL",
      "modelName": "CORSA Mk IV (E) (X15)",
      "typeEngineName": "1.6 VXR",
      "constructionIntervalStart": "2015-04-01",
      "constructionIntervalEnd": null
    },
    {
      "vehicleId": 112130,
      "modelId": 13137,
      "manufacturerName": "OPEL",
      "modelName": "CORSA E (X15)",
      "typeEngineName": "1.4 Turbo (08, 68)",
      "constructionIntervalStart": "2015-03-01",
      "constructionIntervalEnd": null
    },
    {
      "vehicleId": 117747,
      "modelId": 13083,
      "manufacturerName": "VAUXHALL",
      "modelName": "CORSA Mk IV (E) (X15)",
      "typeEngineName": "1.4",
      "constructionIntervalStart": "2015-07-01",
      "constructionIntervalEnd": null
    },
    {
      "vehicleId": 11929,
      "modelId": 9738,
      "manufacturerName": "VAUXHALL",
      "modelName": "ZAFIRA Mk III (P12)",
      "typeEngineName": "1.4 (75)",
      "constructionIntervalStart": "2011-10-01",
      "constructionIntervalEnd": "2018-08-01"
    },
    {
      "vehicleId": 11930,
      "modelId": 9738,
      "manufacturerName": "VAUXHALL",
      "modelName": "ZAFIRA Mk III (P12)",
      "typeEngineName": "1.4 (75)",
      "constructionIntervalStart": "2011-10-01",
      "constructionIntervalEnd": "2018-08-01"
    },
    {
      "vehicleId": 11942,
      "modelId": 7599,
      "manufacturerName": "VAUXHALL",
      "modelName": "INSIGNIA Mk I (A) Saloon (G09)",
      "typeEngineName": "1.4 (69)",
      "constructionIntervalStart": "2011-04-01",
      "constructionIntervalEnd": "2017-05-01"
    },
    {
      "vehicleId": 14189,
      "modelId": 4819,
      "manufacturerName": "VAUXHALL",
      "modelName": "COMBO Mk II (C) Box Body/MPV (F25)",
      "typeEngineName": "1.4 16V",
      "constructionIntervalStart": "2001-10-01",
      "constructionIntervalEnd": "2007-05-01"
    },
    {
      "vehicleId": 14778,
      "modelId": 4633,
      "manufacturerName": "VAUXHALL",
      "modelName": "AGILA Mk I (A) (H00)",
      "typeEngineName": "1.0 12V",
      "constructionIntervalStart": "2000-09-01",
      "constructionIntervalEnd": "2005-08-01"
    },
    {
      "vehicleId": 14934,
      "modelId": 4658,
      "manufacturerName": "VAUXHALL",
      "modelName": "CORSA Mk II (C) (X01)",
      "typeEngineName": "1.0 12V (F08, F68)",
      "constructionIntervalStart": "2000-09-01",
      "constructionIntervalEnd": "2003-10-01"
    },
    {
      "vehicleId": 14779,
      "modelId": 4633,
      "manufacturerName": "VAUXHALL",
      "modelName": "AGILA Mk I (A) (H00)",
      "typeEngineName": "1.2 16V",
      "constructionIntervalStart": "2000-09-01",
      "constructionIntervalEnd": "2008-03-01"
    },
    {
      "vehicleId": 14911,
      "modelId": 4650,
      "manufacturerName": "OPEL",
      "modelName": "CORSA C (X01)",
      "typeEngineName": "1.2 (F08, F68)",
      "constructionIntervalStart": "2000-09-01",
      "constructionIntervalEnd": "2009-12-01"
    },
    {
      "vehicleId": 14935,
      "modelId": 4658,
      "manufacturerName": "VAUXHALL",
      "modelName": "CORSA Mk II (C) (X01)",
      "typeEngineName": "1.2 16V (F08, F68)",
      "constructionIntervalStart": "2000-09-01",
      "constructionIntervalEnd": "2006-10-01"
    },
    {
      "vehicleId": 16151,
      "modelId": 4815,
      "manufacturerName": "VAUXHALL",
      "modelName": "CORSAVAN Mk II (C) Hatchback Van (X01)",
      "typeEngineName": "1.2 16V (F08)",
      "constructionIntervalStart": "2000-09-01",
      "constructionIntervalEnd": "2006-06-01"
    },
    {
      "vehicleId": 18139,
      "modelId": 4658,
      "manufacturerName": "VAUXHALL",
      "modelName": "CORSA Mk II (C) (X01)",
      "typeEngineName": "1.2 16V Dualfuel (F08)",
      "constructionIntervalStart": "2001-08-01",
      "constructionIntervalEnd": "2006-10-01"
    },
    {
      "vehicleId": 18140,
      "modelId": 4815,
      "manufacturerName": "VAUXHALL",
      "modelName": "CORSAVAN Mk II (C) Hatchback Van (X01)",
      "typeEngineName": "1.2 16V Dualfuel (F08)",
      "constructionIntervalStart": "2001-08-01",
      "constructionIntervalEnd": "2006-06-01"
    },
    {
      "vehicleId": 16193,
      "modelId": 4820,
      "manufacturerName": "OPEL",
      "modelName": "CORSA C Hatchback Van (X01)",
      "typeEngineName": "1.2 16V (F08, W5L)",
      "constructionIntervalStart": "2000-09-01",
      "constructionIntervalEnd": "2003-07-01"
    },
    {
      "vehicleId": 18179,
      "modelId": 5154,
      "manufacturerName": "VAUXHALL",
      "modelName": "TIGRA TwinTop (X04)",
      "typeEngineName": "1.4",
      "constructionIntervalStart": "2004-06-01",
      "constructionIntervalEnd": "2009-08-01"
    },
    {
      "vehicleId": 18752,
      "modelId": 4819,
      "manufacturerName": "VAUXHALL",
      "modelName": "COMBO Mk II (C) Box Body/MPV (F25)",
      "typeEngineName": "1.4 i 16V",
      "constructionIntervalStart": "2004-01-01",
      "constructionIntervalEnd": "2011-11-01"
    },
    {
      "vehicleId": 19121,
      "modelId": 5475,
      "manufacturerName": "VAUXHALL",
      "modelName": "ASTRA Mk V (H) Estate (A04)",
      "typeEngineName": "1.4 (L35)",
      "constructionIntervalStart": "2004-08-01",
      "constructionIntervalEnd": "2009-03-01"
    },
    {
      "vehicleId": 19279,
      "modelId": 4820,
      "manufacturerName": "OPEL",
      "modelName": "CORSA C Hatchback Van (X01)",
      "typeEngineName": "1.2 (F08, W5L)",
      "constructionIntervalStart": "2005-07-01",
      "constructionIntervalEnd": "2006-06-01"
    },
    {
      "vehicleId": 20044,
      "modelId": 4633,
      "manufacturerName": "VAUXHALL",
      "modelName": "AGILA Mk I (A) (H00)",
      "typeEngineName": "1.0 12V",
      "constructionIntervalStart": "2000-02-01",
      "constructionIntervalEnd": "2006-11-01"
    },
    {
      "vehicleId": 20046,
      "modelId": 4633,
      "manufacturerName": "VAUXHALL",
      "modelName": "AGILA Mk I (A) (H00)",
      "typeEngineName": "1.2 16V Twinport",
      "constructionIntervalStart": "2004-07-01",
      "constructionIntervalEnd": "2006-11-01"
    },
    {
      "vehicleId": 21481,
      "modelId": 7512,
      "manufacturerName": "SUZUKI",
      "modelName": "WAGON R (MH21, MH22)",
      "typeEngineName": "1.2",
      "constructionIntervalStart": "2004-06-01",
      "constructionIntervalEnd": "2005-08-01"
    },
    {
      "vehicleId": 23660,
      "modelId": 38280,
      "manufacturerName": "OPEL",
      "modelName": "ASTRA G CLASSIC Caravan (F35)",
      "typeEngineName": "1.4 (F35)",
      "constructionIntervalStart": "2007-10-01",
      "constructionIntervalEnd": "2009-07-01"
    },
    {
      "vehicleId": 26744,
      "modelId": 10202,
      "manufacturerName": "VAUXHALL",
      "modelName": "COMBO TOUR Mk II (C) (F25)",
      "typeEngineName": "1.4",
      "constructionIntervalStart": "2004-10-01",
      "constructionIntervalEnd": "2010-09-01"
    },
    {
      "vehicleId": 17574,
      "modelId": 4474,
      "manufacturerName": "OPEL",
      "modelName": "AGILA A (H00)",
      "typeEngineName": "1.0 (F68)",
      "constructionIntervalStart": "2003-08-01",
      "constructionIntervalEnd": "2007-12-01"
    },
    {
      "vehicleId": 18230,
      "modelId": 4474,
      "manufacturerName": "OPEL",
      "modelName": "AGILA A (H00)",
      "typeEngineName": "1.2 16V Twinport (F68)",
      "constructionIntervalStart": "2004-07-01",
      "constructionIntervalEnd": "2007-12-01"
    },
    {
      "vehicleId": 18115,
      "modelId": 5148,
      "manufacturerName": "VAUXHALL",
      "modelName": "ASTRA Mk V (H) (A04)",
      "typeEngineName": "1.4 (L48)",
      "constructionIntervalStart": "2004-01-01",
      "constructionIntervalEnd": "2009-05-01"
    },
    {
      "vehicleId": 18177,
      "modelId": 5153,
      "manufacturerName": "OPEL",
      "modelName": "TIGRA TwinTop (X04)",
      "typeEngineName": "1.4 (R97)",
      "constructionIntervalStart": "2004-06-01",
      "constructionIntervalEnd": "2010-12-01"
    },
    {
      "vehicleId": 18229,
      "modelId": 4650,
      "manufacturerName": "OPEL",
      "modelName": "CORSA C (X01)",
      "typeEngineName": "1.2 Twinport (F08, F68)",
      "constructionIntervalStart": "2004-07-01",
      "constructionIntervalEnd": "2009-12-01"
    },
    {
      "vehicleId": 18295,
      "modelId": 5209,
      "manufacturerName": "OPEL",
      "modelName": "ASTRA H GTC (A04)",
      "typeEngineName": "1.4 (L08)",
      "constructionIntervalStart": "2005-03-01",
      "constructionIntervalEnd": "2010-10-01"
    },
    {
      "vehicleId": 18557,
      "modelId": 4982,
      "manufacturerName": "OPEL",
      "modelName": "COMBO Tour",
      "typeEngineName": "1.4",
      "constructionIntervalStart": "2004-10-01",
      "constructionIntervalEnd": "2011-12-01"
    },
    {
      "vehicleId": 19146,
      "modelId": 4818,
      "manufacturerName": "OPEL",
      "modelName": "COMBO Box Body/MPV",
      "typeEngineName": "1.4 16V",
      "constructionIntervalStart": "2005-08-01",
      "constructionIntervalEnd": null
    },
    {
      "vehicleId": 19308,
      "modelId": 5518,
      "manufacturerName": "VAUXHALL",
      "modelName": "ZAFIRA Mk II (B) (A05)",
      "typeEngineName": "1.8",
      "constructionIntervalStart": "2005-04-01",
      "constructionIntervalEnd": "2014-11-01"
    },
    {
      "vehicleId": 19361,
      "modelId": 4956,
      "manufacturerName": "OPEL",
      "modelName": "SIGNUM Hatchback (Z03)",
      "typeEngineName": "1.8 (F48)",
      "constructionIntervalStart": "2005-09-01",
      "constructionIntervalEnd": "2008-12-01"
    },
    {
      "vehicleId": 19722,
      "modelId": 5598,
      "manufacturerName": "OPEL",
      "modelName": "CORSA D (S07)",
      "typeEngineName": "1.0 (L08, L68)",
      "constructionIntervalStart": "2006-07-01",
      "constructionIntervalEnd": "2010-12-01"
    },
    {
      "vehicleId": 19724,
      "modelId": 5598,
      "manufacturerName": "OPEL",
      "modelName": "CORSA D (S07)",
      "typeEngineName": "1.4 LPG (L08, L68)",
      "constructionIntervalStart": "2006-08-01",
      "constructionIntervalEnd": "2011-12-01"
    },
    {
      "vehicleId": 19816,
      "modelId": 5449,
      "manufacturerName": "FIAT",
      "modelName": "CROMA (194_)",
      "typeEngineName": "1.8 16V (194AXG1A)",
      "constructionIntervalStart": "2005-12-01",
      "constructionIntervalEnd": "2011-12-01"
    },
    {
      "vehicleId": 20010,
      "modelId": 5145,
      "manufacturerName": "OPEL",
      "modelName": "ASTRA H Estate (A04)",
      "typeEngineName": "1.8 (L35)",
      "constructionIntervalStart": "2005-08-01",
      "constructionIntervalEnd": "2014-05-01"
    },
    {
      "vehicleId": 125945,
      "modelId": 37067,
      "manufacturerName": "OPEL",
      "modelName": "ASTRA H CLASSIC Hatchback (A04)",
      "typeEngineName": "1.8 (L48)",
      "constructionIntervalStart": "2013-02-01",
      "constructionIntervalEnd": null
    },
    {
      "vehicleId": 129089,
      "modelId": 37112,
      "manufacturerName": "OPEL",
      "modelName": "ASTRA H CLASSIC Estate (A04)",
      "typeEngineName": "1.8 (L35)",
      "constructionIntervalStart": "2012-01-01",
      "constructionIntervalEnd": "2014-05-01"
    },
    {
      "vehicleId": 22675,
      "modelId": 5598,
      "manufacturerName": "OPEL",
      "modelName": "CORSA D (S07)",
      "typeEngineName": "1.6 Turbo (L08, L68)",
      "constructionIntervalStart": "2006-11-01",
      "constructionIntervalEnd": "2014-08-01"
    },
    {
      "vehicleId": 22676,
      "modelId": 5098,
      "manufacturerName": "OPEL",
      "modelName": "ASTRA H (A04)",
      "typeEngineName": "1.6 Turbo (L48)",
      "constructionIntervalStart": "2007-02-01",
      "constructionIntervalEnd": "2010-10-01"
    },
    {
      "vehicleId": 22678,
      "modelId": 5145,
      "manufacturerName": "OPEL",
      "modelName": "ASTRA H Estate (A04)",
      "typeEngineName": "1.6 Turbo (L35)",
      "constructionIntervalStart": "2007-02-01",
      "constructionIntervalEnd": "2010-10-01"
    },
    {
      "vehicleId": 22679,
      "modelId": 5209,
      "manufacturerName": "OPEL",
      "modelName": "ASTRA H GTC (A04)",
      "typeEngineName": "1.6 Turbo (L08)",
      "constructionIntervalStart": "2007-02-01",
      "constructionIntervalEnd": "2010-10-01"
    },
    {
      "vehicleId": 22680,
      "modelId": 5209,
      "manufacturerName": "OPEL",
      "modelName": "ASTRA H GTC (A04)",
      "typeEngineName": "1.6 (L08)",
      "constructionIntervalStart": "2006-12-01",
      "constructionIntervalEnd": "2010-10-01"
    },
    {
      "vehicleId": 22682,
      "modelId": 5098,
      "manufacturerName": "OPEL",
      "modelName": "ASTRA H (A04)",
      "typeEngineName": "1.6 (L48)",
      "constructionIntervalStart": "2006-12-01",
      "constructionIntervalEnd": "2014-05-01"
    },
    {
      "vehicleId": 22683,
      "modelId": 5145,
      "manufacturerName": "OPEL",
      "modelName": "ASTRA H Estate (A04)",
      "typeEngineName": "1.6 (L35)",
      "constructionIntervalStart": "2006-12-01",
      "constructionIntervalEnd": "2014-05-01"
    },
    {
      "vehicleId": 22684,
      "modelId": 5453,
      "manufacturerName": "OPEL",
      "modelName": "ASTRA H TwinTop (A04)",
      "typeEngineName": "1.6 (L67)",
      "constructionIntervalStart": "2006-12-01",
      "constructionIntervalEnd": "2010-10-01"
    },
    {
      "vehicleId": 23269,
      "modelId": 6413,
      "manufacturerName": "VAUXHALL",
      "modelName": "CORSA Mk III (D) (S07)",
      "typeEngineName": "1.0 (L08)",
      "constructionIntervalStart": "2006-08-01",
      "constructionIntervalEnd": "2014-08-01"
    },
    {
      "vehicleId": 23271,
      "modelId": 6413,
      "manufacturerName": "VAUXHALL",
      "modelName": "CORSA Mk III (D) (S07)",
      "typeEngineName": "1.4 (L08)",
      "constructionIntervalStart": "2006-08-01",
      "constructionIntervalEnd": "2014-08-01"
    },
    {
      "vehicleId": 54974,
      "modelId": 6413,
      "manufacturerName": "VAUXHALL",
      "modelName": "CORSA Mk III (D) (S07)",
      "typeEngineName": "1.4 LPG (L08)",
      "constructionIntervalStart": "2006-07-01",
      "constructionIntervalEnd": "2014-08-01"
    },
    {
      "vehicleId": 23355,
      "modelId": 5543,
      "manufacturerName": "ALFA ROMEO",
      "modelName": "159 Sportwagon (939_)",
      "typeEngineName": "1.8 MPI (939BXL1A)",
      "constructionIntervalStart": "2005-06-01",
      "constructionIntervalEnd": "2011-11-01"
    },
    {
      "vehicleId": 23659,
      "modelId": 3405,
      "manufacturerName": "OPEL",
      "modelName": "ASTRA G Hatchback (T98)",
      "typeEngineName": "1.4 (F08, F48)",
      "constructionIntervalStart": "2007-09-01",
      "constructionIntervalEnd": "2009-12-01"
    },
    {
      "vehicleId": 23685,
      "modelId": 3878,
      "manufacturerName": "OPEL",
      "modelName": "ASTRA G Saloon (T98)",
      "typeEngineName": "1.4 (F69)",
      "constructionIntervalStart": "2007-09-01",
      "constructionIntervalEnd": "2009-12-01"
    },
    {
      "vehicleId": 24670,
      "modelId": 4658,
      "manufacturerName": "VAUXHALL",
      "modelName": "CORSA Mk II (C) (X01)",
      "typeEngineName": "1.0 12V (F08, F68)",
      "constructionIntervalStart": "2003-11-01",
      "constructionIntervalEnd": "2006-10-01"
    },
    {
      "vehicleId": 28826,
      "modelId": 4815,
      "manufacturerName": "VAUXHALL",
      "modelName": "CORSAVAN Mk II (C) Hatchback Van (X01)",
      "typeEngineName": "1.4 (F08)",
      "constructionIntervalStart": "2003-11-01",
      "constructionIntervalEnd": "2006-06-01"
    },
    {
      "vehicleId": 26604,
      "modelId": 7372,
      "manufacturerName": "CHEVROLET",
      "modelName": "AVEO / KALOS Hatchback (T250, T255)",
      "typeEngineName": "1.4",
      "constructionIntervalStart": "2008-04-01",
      "constructionIntervalEnd": null
    },
    {
      "vehicleId": 28009,
      "modelId": 5098,
      "manufacturerName": "OPEL",
      "modelName": "ASTRA H (A04)",
      "typeEngineName": "1.2 (L48)",
      "constructionIntervalStart": "2005-08-01",
      "constructionIntervalEnd": "2010-10-01"
    },
    {
      "vehicleId": 28029,
      "modelId": 5531,
      "manufacturerName": "VAUXHALL",
      "modelName": "ASTRA Mk V (H) Sport Hatch (A04)",
      "typeEngineName": "1.6 (L08)",
      "constructionIntervalStart": "2006-10-01",
      "constructionIntervalEnd": "2010-11-01"
    },
    {
      "vehicleId": 28215,
      "modelId": 7581,
      "manufacturerName": "OPEL",
      "modelName": "INSIGNIA A (G09)",
      "typeEngineName": "1.8 (68)",
      "constructionIntervalStart": "2008-07-01",
      "constructionIntervalEnd": "2017-03-01"
    },
    {
      "vehicleId": 28222,
      "modelId": 7582,
      "manufacturerName": "OPEL",
      "modelName": "INSIGNIA A Saloon (G09)",
      "typeEngineName": "1.8 (69)",
      "constructionIntervalStart": "2008-07-01",
      "constructionIntervalEnd": "2017-03-01"
    },
    {
      "vehicleId": 28836,
      "modelId": 5148,
      "manufacturerName": "VAUXHALL",
      "modelName": "ASTRA Mk V (H) (A04)",
      "typeEngineName": "1.6 (L48)",
      "constructionIntervalStart": "2004-01-01",
      "constructionIntervalEnd": "2009-05-01"
    },
    {
      "vehicleId": 28837,
      "modelId": 5148,
      "manufacturerName": "VAUXHALL",
      "modelName": "ASTRA Mk V (H) (A04)",
      "typeEngineName": "1.8 (L48)",
      "constructionIntervalStart": "2004-01-01",
      "constructionIntervalEnd": "2009-05-01"
    },
    {
      "vehicleId": 28841,
      "modelId": 5475,
      "manufacturerName": "VAUXHALL",
      "modelName": "ASTRA Mk V (H) Estate (A04)",
      "typeEngineName": "1.6 (L35)",
      "constructionIntervalStart": "2004-08-01",
      "constructionIntervalEnd": "2009-03-01"
    },
    {
      "vehicleId": 29401,
      "modelId": 10731,
      "manufacturerName": "OPEL",
      "modelName": "ADAM (M13)",
      "typeEngineName": "1.4 LPG",
      "constructionIntervalStart": "2013-07-01",
      "constructionIntervalEnd": "2018-11-01"
    },
    {
      "vehicleId": 29924,
      "modelId": 7861,
      "manufacturerName": "OPEL",
      "modelName": "INSIGNIA A Sports Tourer (G09)",
      "typeEngineName": "1.8 (35)",
      "constructionIntervalStart": "2008-07-01",
      "constructionIntervalEnd": "2017-03-01"
    },
    {
      "vehicleId": 29933,
      "modelId": 7862,
      "manufacturerName": "VAUXHALL",
      "modelName": "INSIGNIA Mk I (A) Hatchback (G09)",
      "typeEngineName": "1.8 (68)",
      "constructionIntervalStart": "2008-07-01",
      "constructionIntervalEnd": "2017-05-01"
    },
    {
      "vehicleId": 30673,
      "modelId": 6413,
      "manufacturerName": "VAUXHALL",
      "modelName": "CORSA Mk III (D) (S07)",
      "typeEngineName": "1.6 SRi (L08)",
      "constructionIntervalStart": "2007-05-01",
      "constructionIntervalEnd": "2014-08-01"
    },
    {
      "vehicleId": 30674,
      "modelId": 5519,
      "manufacturerName": "VAUXHALL",
      "modelName": "ASTRA Mk V (H) TwinTop (A04)",
      "typeEngineName": "1.6 i 16V (L67)",
      "constructionIntervalStart": "2006-10-01",
      "constructionIntervalEnd": "2011-08-01"
    },
    {
      "vehicleId": 31397,
      "modelId": 5519,
      "manufacturerName": "VAUXHALL",
      "modelName": "ASTRA Mk V (H) TwinTop (A04)",
      "typeEngineName": "1.8 (L67)",
      "constructionIntervalStart": "2008-05-01",
      "constructionIntervalEnd": "2010-11-01"
    },
    {
      "vehicleId": 31469,
      "modelId": 8127,
      "manufacturerName": "CHEVROLET",
      "modelName": "CRUZE (J300)",
      "typeEngineName": "1.6",
      "constructionIntervalStart": "2009-05-01",
      "constructionIntervalEnd": null
    },
    {
      "vehicleId": 31470,
      "modelId": 8127,
      "manufacturerName": "CHEVROLET",
      "modelName": "CRUZE (J300)",
      "typeEngineName": "1.8",
      "constructionIntervalStart": "2009-05-01",
      "constructionIntervalEnd": null
    },
    {
      "vehicleId": 31756,
      "modelId": 7565,
      "manufacturerName": "HOLDEN",
      "modelName": "ASTRA SPORTSBACK (AH)",
      "typeEngineName": "1.8 i",
      "constructionIntervalStart": "2007-04-01",
      "constructionIntervalEnd": "2010-03-01"
    },
    {
      "vehicleId": 31950,
      "modelId": 7564,
      "manufacturerName": "HOLDEN",
      "modelName": "ASTRA (AH)",
      "typeEngineName": "1.8 i",
      "constructionIntervalStart": "2007-04-01",
      "constructionIntervalEnd": "2010-03-01"
    },
    {
      "vehicleId": 31953,
      "modelId": 8185,
      "manufacturerName": "HOLDEN",
      "modelName": "ASTRA Estate (AH)",
      "typeEngineName": "1.8 i",
      "constructionIntervalStart": "2007-04-01",
      "constructionIntervalEnd": "2010-03-01"
    },
    {
      "vehicleId": 31968,
      "modelId": 5598,
      "manufacturerName": "OPEL",
      "modelName": "CORSA D (S07)",
      "typeEngineName": "1.2 LPG (L08, L68)",
      "constructionIntervalStart": "2006-08-01",
      "constructionIntervalEnd": "2014-08-01"
    },
    {
      "vehicleId": 31982,
      "modelId": 5475,
      "manufacturerName": "VAUXHALL",
      "modelName": "ASTRA Mk V (H) Estate (A04)",
      "typeEngineName": "1.8 (L35)",
      "constructionIntervalStart": "2005-12-01",
      "constructionIntervalEnd": "2010-10-01"
    },
    {
      "vehicleId": 32007,
      "modelId": 8248,
      "manufacturerName": "HOLDEN",
      "modelName": "CRUZE Saloon (JG)",
      "typeEngineName": "1.8 i",
      "constructionIntervalStart": "2009-06-01",
      "constructionIntervalEnd": "2011-03-01"
    },
    {
      "vehicleId": 32149,
      "modelId": 8301,
      "manufacturerName": "VAUXHALL",
      "modelName": "ASTRA Mk VI (J) (P10)",
      "typeEngineName": "1.4 Turbo",
      "constructionIntervalStart": "2009-12-01",
      "constructionIntervalEnd": "2015-10-01"
    },
    {
      "vehicleId": 33060,
      "modelId": 8549,
      "manufacturerName": "OPEL",
      "modelName": "MERIVA B MPV (S10)",
      "typeEngineName": "1.4 (75)",
      "constructionIntervalStart": "2010-06-01",
      "constructionIntervalEnd": "2017-03-01"
    },
    {
      "vehicleId": 56774,
      "modelId": 10351,
      "manufacturerName": "OPEL",
      "modelName": "ASTRA J Saloon",
      "typeEngineName": "1.4 Turbo (69)",
      "constructionIntervalStart": "2012-06-01",
      "constructionIntervalEnd": "2015-10-01"
    },
    {
      "vehicleId": 33739,
      "modelId": 5531,
      "manufacturerName": "VAUXHALL",
      "modelName": "ASTRA Mk V (H) Sport Hatch (A04)",
      "typeEngineName": "1.6 i 16V (L08)",
      "constructionIntervalStart": "2006-12-01",
      "constructionIntervalEnd": "2010-11-01"
    },
    {
      "vehicleId": 33751,
      "modelId": 8759,
      "manufacturerName": "VAUXHALL",
      "modelName": "CORSAVAN Mk III (D) Hatchback Van (S07)",
      "typeEngineName": "1.2",
      "constructionIntervalStart": "2010-01-01",
      "constructionIntervalEnd": null
    },
    {
      "vehicleId": 51391,
      "modelId": 8127,
      "manufacturerName": "CHEVROLET",
      "modelName": "CRUZE (J300)",
      "typeEngineName": "1.4",
      "constructionIntervalStart": "2010-09-01",
      "constructionIntervalEnd": null
    },
    {
      "vehicleId": 55118,
      "modelId": 10264,
      "manufacturerName": "OPEL",
      "modelName": "MOKKA / MOKKA X (J13)",
      "typeEngineName": "1.4 4x4 (_76)",
      "constructionIntervalStart": "2012-06-01",
      "constructionIntervalEnd": "2019-12-01"
    },
    {
      "vehicleId": 55119,
      "modelId": 10264,
      "manufacturerName": "OPEL",
      "modelName": "MOKKA / MOKKA X (J13)",
      "typeEngineName": "1.6 (_76)",
      "constructionIntervalStart": "2012-06-01",
      "constructionIntervalEnd": "2019-12-01"
    },
    {
      "vehicleId": 55295,
      "modelId": 10325,
      "manufacturerName": "VAUXHALL",
      "modelName": "MOKKA / MOKKA X (J13)",
      "typeEngineName": "1.4 4x4",
      "constructionIntervalStart": "2012-06-01",
      "constructionIntervalEnd": "2019-12-01"
    },
    {
      "vehicleId": 55296,
      "modelId": 10325,
      "manufacturerName": "VAUXHALL",
      "modelName": "MOKKA / MOKKA X (J13)",
      "typeEngineName": "1.6",
      "constructionIntervalStart": "2012-06-01",
      "constructionIntervalEnd": "2019-12-01"
    },
    {
      "vehicleId": 55194,
      "modelId": 8127,
      "manufacturerName": "CHEVROLET",
      "modelName": "CRUZE (J300)",
      "typeEngineName": "1.8",
      "constructionIntervalStart": "2009-11-01",
      "constructionIntervalEnd": null
    },
    {
      "vehicleId": 55379,
      "modelId": 10351,
      "manufacturerName": "OPEL",
      "modelName": "ASTRA J Saloon",
      "typeEngineName": "1.4 (69)",
      "constructionIntervalStart": "2012-06-01",
      "constructionIntervalEnd": "2015-10-01"
    },
    {
      "vehicleId": 55380,
      "modelId": 10351,
      "manufacturerName": "OPEL",
      "modelName": "ASTRA J Saloon",
      "typeEngineName": "1.6 Turbo (69)",
      "constructionIntervalStart": "2012-06-01",
      "constructionIntervalEnd": null
    },
    {
      "vehicleId": 107481,
      "modelId": 10351,
      "manufacturerName": "OPEL",
      "modelName": "ASTRA J Saloon",
      "typeEngineName": "1.4 LPG (69)",
      "constructionIntervalStart": "2014-07-01",
      "constructionIntervalEnd": null
    },
    {
      "vehicleId": 55381,
      "modelId": 10351,
      "manufacturerName": "OPEL",
      "modelName": "ASTRA J Saloon",
      "typeEngineName": "1.6 (69)",
      "constructionIntervalStart": "2012-06-01",
      "constructionIntervalEnd": null
    },
    {
      "vehicleId": 55382,
      "modelId": 10351,
      "manufacturerName": "OPEL",
      "modelName": "ASTRA J Saloon",
      "typeEngineName": "1.4 Turbo (69)",
      "constructionIntervalStart": "2012-06-01",
      "constructionIntervalEnd": null
    },
    {
      "vehicleId": 55461,
      "modelId": 8127,
      "manufacturerName": "CHEVROLET",
      "modelName": "CRUZE (J300)",
      "typeEngineName": "1.4",
      "constructionIntervalStart": "2013-07-01",
      "constructionIntervalEnd": null
    },
    {
      "vehicleId": 55465,
      "modelId": 9625,
      "manufacturerName": "CHEVROLET",
      "modelName": "CRUZE Hatchback (J305)",
      "typeEngineName": "1.4",
      "constructionIntervalStart": "2013-07-01",
      "constructionIntervalEnd": "2015-12-01"
    },
    {
      "vehicleId": 55475,
      "modelId": 10516,
      "manufacturerName": "CHEVROLET",
      "modelName": "CRUZE Station Wagon (J308)",
      "typeEngineName": "1.4",
      "constructionIntervalStart": "2013-07-01",
      "constructionIntervalEnd": "2015-12-01"
    },
    {
      "vehicleId": 55800,
      "modelId": 10516,
      "manufacturerName": "CHEVROLET",
      "modelName": "CRUZE Station Wagon (J308)",
      "typeEngineName": "1.8",
      "constructionIntervalStart": "2012-08-01",
      "constructionIntervalEnd": null
    },
    {
      "vehicleId": 55799,
      "modelId": 10516,
      "manufacturerName": "CHEVROLET",
      "modelName": "CRUZE Station Wagon (J308)",
      "typeEngineName": "1.6",
      "constructionIntervalStart": "2012-08-01",
      "constructionIntervalEnd": "2015-12-01"
    },
    {
      "vehicleId": 56419,
      "modelId": 10640,
      "manufacturerName": "VAUXHALL",
      "modelName": "ADAM (M13)",
      "typeEngineName": "1.2",
      "constructionIntervalStart": "2012-10-01",
      "constructionIntervalEnd": "2019-04-01"
    },
    {
      "vehicleId": 56420,
      "modelId": 10640,
      "manufacturerName": "VAUXHALL",
      "modelName": "ADAM (M13)",
      "typeEngineName": "1.4",
      "constructionIntervalStart": "2012-10-01",
      "constructionIntervalEnd": "2019-02-01"
    },
    {
      "vehicleId": 56421,
      "modelId": 10640,
      "manufacturerName": "VAUXHALL",
      "modelName": "ADAM (M13)",
      "typeEngineName": "1.4",
      "constructionIntervalStart": "2012-10-01",
      "constructionIntervalEnd": "2019-02-01"
    },
    {
      "vehicleId": 56729,
      "modelId": 10731,
      "manufacturerName": "OPEL",
      "modelName": "ADAM (M13)",
      "typeEngineName": "1.2",
      "constructionIntervalStart": "2012-10-01",
      "constructionIntervalEnd": "2019-02-01"
    },
    {
      "vehicleId": 56730,
      "modelId": 10731,
      "manufacturerName": "OPEL",
      "modelName": "ADAM (M13)",
      "typeEngineName": "1.4",
      "constructionIntervalStart": "2012-10-01",
      "constructionIntervalEnd": "2019-02-01"
    },
    {
      "vehicleId": 56731,
      "modelId": 10731,
      "manufacturerName": "OPEL",
      "modelName": "ADAM (M13)",
      "typeEngineName": "1.4",
      "constructionIntervalStart": "2012-10-01",
      "constructionIntervalEnd": "2019-02-01"
    },
    {
      "vehicleId": 56786,
      "modelId": 7861,
      "manufacturerName": "OPEL",
      "modelName": "INSIGNIA A Sports Tourer (G09)",
      "typeEngineName": "1.4 LPG (35)",
      "constructionIntervalStart": "2012-09-01",
      "constructionIntervalEnd": "2017-03-01"
    },
    {
      "vehicleId": 57390,
      "modelId": 9625,
      "manufacturerName": "CHEVROLET",
      "modelName": "CRUZE Hatchback (J305)",
      "typeEngineName": "1.8 LPG",
      "constructionIntervalStart": "2011-06-01",
      "constructionIntervalEnd": "2015-12-01"
    },
    {
      "vehicleId": 57414,
      "modelId": 9625,
      "manufacturerName": "CHEVROLET",
      "modelName": "CRUZE Hatchback (J305)",
      "typeEngineName": "1.6",
      "constructionIntervalStart": "2012-12-01",
      "constructionIntervalEnd": null
    },
    {
      "vehicleId": 57568,
      "modelId": 5878,
      "manufacturerName": "CHEVROLET",
      "modelName": "ASTRA Saloon",
      "typeEngineName": "1.8",
      "constructionIntervalStart": "2006-08-01",
      "constructionIntervalEnd": "2009-03-01"
    },
    {
      "vehicleId": 58154,
      "modelId": 10971,
      "manufacturerName": "VAUXHALL",
      "modelName": "CASCADA Convertible (W13)",
      "typeEngineName": "1.4",
      "constructionIntervalStart": "2013-02-01",
      "constructionIntervalEnd": null
    },
    {
      "vehicleId": 59073,
      "modelId": 10819,
      "manufacturerName": "CHEVROLET",
      "modelName": "TRAX",
      "typeEngineName": "1.4",
      "constructionIntervalStart": "2012-12-01",
      "constructionIntervalEnd": null
    },
    {
      "vehicleId": 100745,
      "modelId": 10819,
      "manufacturerName": "CHEVROLET",
      "modelName": "TRAX",
      "typeEngineName": "1.4 LPG",
      "constructionIntervalStart": "2013-04-01",
      "constructionIntervalEnd": null
    },
    {
      "vehicleId": 59332,
      "modelId": 5148,
      "manufacturerName": "VAUXHALL",
      "modelName": "ASTRA Mk V (H) (A04)",
      "typeEngineName": "1.6 Turbo (L48)",
      "constructionIntervalStart": "2006-09-01",
      "constructionIntervalEnd": "2009-09-01"
    },
    {
      "vehicleId": 100585,
      "modelId": 9625,
      "manufacturerName": "CHEVROLET",
      "modelName": "CRUZE Hatchback (J305)",
      "typeEngineName": "1.8",
      "constructionIntervalStart": "2011-10-01",
      "constructionIntervalEnd": null
    },
    {
      "vehicleId": 100739,
      "modelId": 10264,
      "manufacturerName": "OPEL",
      "modelName": "MOKKA / MOKKA X (J13)",
      "typeEngineName": "1.4 LPG (_76)",
      "constructionIntervalStart": "2013-04-01",
      "constructionIntervalEnd": "2019-12-01"
    },
    {
      "vehicleId": 107552,
      "modelId": 13083,
      "manufacturerName": "VAUXHALL",
      "modelName": "CORSA Mk IV (E) (X15)",
      "typeEngineName": "1.2",
      "constructionIntervalStart": "2014-08-01",
      "constructionIntervalEnd": null
    },
    {
      "vehicleId": 107554,
      "modelId": 13083,
      "manufacturerName": "VAUXHALL",
      "modelName": "CORSA Mk IV (E) (X15)",
      "typeEngineName": "1.4",
      "constructionIntervalStart": "2014-08-01",
      "constructionIntervalEnd": null
    },
    {
      "vehicleId": 112128,
      "modelId": 13137,
      "manufacturerName": "OPEL",
      "modelName": "CORSA E (X15)",
      "typeEngineName": "1.4 LPG (08, 68)",
      "constructionIntervalStart": "2015-03-01",
      "constructionIntervalEnd": null
    },
    {
      "vehicleId": 120359,
      "modelId": 13137,
      "manufacturerName": "OPEL",
      "modelName": "CORSA E (X15)",
      "typeEngineName": "1.4 LPG (08, 68)",
      "constructionIntervalStart": "2015-11-01",
      "constructionIntervalEnd": null
    },
    {
      "vehicleId": 107796,
      "modelId": 13137,
      "manufacturerName": "OPEL",
      "modelName": "CORSA E (X15)",
      "typeEngineName": "1.4 (08, 68)",
      "constructionIntervalStart": "2014-09-01",
      "constructionIntervalEnd": null
    },
    {
      "vehicleId": 108277,
      "modelId": 13137,
      "manufacturerName": "OPEL",
      "modelName": "CORSA E (X15)",
      "typeEngineName": "1.4 (08, 68)",
      "constructionIntervalStart": "2014-09-01",
      "constructionIntervalEnd": null
    },
    {
      "vehicleId": 110031,
      "modelId": 13635,
      "manufacturerName": "OPEL",
      "modelName": "CORSA E Hatchback Van (X15)",
      "typeEngineName": "1.4 (08)",
      "constructionIntervalStart": "2014-09-01",
      "constructionIntervalEnd": null
    },
    {
      "vehicleId": 110033,
      "modelId": 13635,
      "manufacturerName": "OPEL",
      "modelName": "CORSA E Hatchback Van (X15)",
      "typeEngineName": "1.4 (08)",
      "constructionIntervalStart": "2014-09-01",
      "constructionIntervalEnd": null
    },
    {
      "vehicleId": 112141,
      "modelId": 13137,
      "manufacturerName": "OPEL",
      "modelName": "CORSA E (X15)",
      "typeEngineName": "1.6 Turbo (08, 68)",
      "constructionIntervalStart": "2015-03-01",
      "constructionIntervalEnd": null
    },
    {
      "vehicleId": 118824,
      "modelId": 13083,
      "manufacturerName": "VAUXHALL",
      "modelName": "CORSA Mk IV (E) (X15)",
      "typeEngineName": "1.4",
      "constructionIntervalStart": "2014-09-01",
      "constructionIntervalEnd": null
    },
    {
      "vehicleId": 123048,
      "modelId": 37112,
      "manufacturerName": "OPEL",
      "modelName": "ASTRA H CLASSIC Estate (A04)",
      "typeEngineName": "1.6 (L35)",
      "constructionIntervalStart": "2006-12-01",
      "constructionIntervalEnd": "2014-05-01"
    },
    {
      "vehicleId": 132752,
      "modelId": 9183,
      "manufacturerName": "OPEL",
      "modelName": "ASTRA H Estate Van (L70)",
      "typeEngineName": "1.6 EcoTec (L70)",
      "constructionIntervalStart": "2006-10-01",
      "constructionIntervalEnd": "2010-12-01"
    },
    {
      "vehicleId": 128502,
      "modelId": 5425,
      "manufacturerName": "OPEL",
      "modelName": "ZAFIRA / ZAFIRA FAMILY B (A05)",
      "typeEngineName": "1.8 LPG (M75)",
      "constructionIntervalStart": "2009-07-01",
      "constructionIntervalEnd": "2015-04-01"
    },
    {
      "vehicleId": 129002,
      "modelId": 4815,
      "manufacturerName": "VAUXHALL",
      "modelName": "CORSAVAN Mk II (C) Hatchback Van (X01)",
      "typeEngineName": "1.2 16V Dualfuel (F08)",
      "constructionIntervalStart": "2004-07-01",
      "constructionIntervalEnd": "2005-12-01"
    },
    {
      "vehicleId": 132795,
      "modelId": 9180,
      "manufacturerName": "OPEL",
      "modelName": "CORSA D Hatchback Van (S07)",
      "typeEngineName": "1.6 (L08)",
      "constructionIntervalStart": "2012-07-01",
      "constructionIntervalEnd": "2014-08-01"
    },
    {
      "vehicleId": 141493,
      "modelId": 4666,
      "manufacturerName": "SUZUKI",
      "modelName": "WAGON R+ (MA)",
      "typeEngineName": "1.2 (RB 412)",
      "constructionIntervalStart": "2005-01-01",
      "constructionIntervalEnd": "2008-12-01"
    },
    {
      "vehicleId": 127363,
      "modelId": 5556,
      "manufacturerName": "CHEVROLET",
      "modelName": "AVEO / KALOS Saloon (T250, T255)",
      "typeEngineName": "1.6",
      "constructionIntervalStart": "2008-01-01",
      "constructionIntervalEnd": "2012-12-01"
    },
    {
      "vehicleId": 10703,
      "modelId": 5556,
      "manufacturerName": "CHEVROLET",
      "modelName": "AVEO / KALOS Saloon (T250, T255)",
      "typeEngineName": "1.6",
      "constructionIntervalStart": "2008-01-01",
      "constructionIntervalEnd": null
    },
    {
      "vehicleId": 138319,
      "modelId": 8127,
      "manufacturerName": "CHEVROLET",
      "modelName": "CRUZE (J300)",
      "typeEngineName": "1.6",
      "constructionIntervalStart": "2012-12-01",
      "constructionIntervalEnd": null
    },
    {
      "vehicleId": 10352,
      "modelId": 9625,
      "manufacturerName": "CHEVROLET",
      "modelName": "CRUZE Hatchback (J305)",
      "typeEngineName": "1.6",
      "constructionIntervalStart": "2011-06-01",
      "constructionIntervalEnd": null
    },
    {
      "vehicleId": 134804,
      "modelId": 9625,
      "manufacturerName": "CHEVROLET",
      "modelName": "CRUZE Hatchback (J305)",
      "typeEngineName": "1.6",
      "constructionIntervalStart": "2012-12-01",
      "constructionIntervalEnd": null
    },
    {
      "vehicleId": 59054,
      "modelId": 10819,
      "manufacturerName": "CHEVROLET",
      "modelName": "TRAX",
      "typeEngineName": "1.8",
      "constructionIntervalStart": "2013-03-01",
      "constructionIntervalEnd": null
    },
    {
      "vehicleId": 5714,
      "modelId": 9083,
      "manufacturerName": "CHEVROLET",
      "modelName": "ORLANDO (J309)",
      "typeEngineName": "1.8",
      "constructionIntervalStart": "2011-02-01",
      "constructionIntervalEnd": null
    },
    {
      "vehicleId": 59055,
      "modelId": 10819,
      "manufacturerName": "CHEVROLET",
      "modelName": "TRAX",
      "typeEngineName": "1.8 AWD",
      "constructionIntervalStart": "2013-03-01",
      "constructionIntervalEnd": null
    },
    {
      "vehicleId": 59811,
      "modelId": 5556,
      "manufacturerName": "CHEVROLET",
      "modelName": "AVEO / KALOS Saloon (T250, T255)",
      "typeEngineName": "1.6",
      "constructionIntervalStart": "2007-01-01",
      "constructionIntervalEnd": null
    },
    {
      "vehicleId": 55798,
      "modelId": 10516,
      "manufacturerName": "CHEVROLET",
      "modelName": "CRUZE Station Wagon (J308)",
      "typeEngineName": "1.4",
      "constructionIntervalStart": "2012-08-01",
      "constructionIntervalEnd": null
    },
    {
      "vehicleId": 50857,
      "modelId": 8754,
      "manufacturerName": "VAUXHALL",
      "modelName": "MERIVA Mk II (B) (S10)",
      "typeEngineName": "1.4 LPG",
      "constructionIntervalStart": "2011-06-01",
      "constructionIntervalEnd": "2017-03-01"
    },
    {
      "vehicleId": 10443,
      "modelId": 9592,
      "manufacturerName": "CHEVROLET",
      "modelName": "AVEO Saloon (T300)",
      "typeEngineName": "1.6",
      "constructionIntervalStart": "2011-03-01",
      "constructionIntervalEnd": null
    },
    {
      "vehicleId": 107795,
      "modelId": 13137,
      "manufacturerName": "OPEL",
      "modelName": "CORSA E (X15)",
      "typeEngineName": "1.2 (08, 68)",
      "constructionIntervalStart": "2014-09-01",
      "constructionIntervalEnd": null
    }
  ],
  "specs": [
    {
      "criteriaName": "Height [mm]",
      "criteriaValue": "106"
    },
    {
      "criteriaName": "Height 1 [mm]",
      "criteriaValue": "96"
    },
    {
      "criteriaName": "Outer Diameter [mm]",
      "criteriaValue": "58"
    },
    {
      "criteriaName": "Supplementary Article/Supplementary Info",
      "criteriaValue": "35"
    },
    {
      "criteriaName": "Filter type",
      "criteriaValue": "9"
    },
    {
      "criteriaName": "Outer Diameter 2 [mm]",
      "criteriaValue": "21"
    },
    {
      "criteriaName": "Inner Diameter 1 [mm]",
      "criteriaValue": "27"
    }
  ],
  "oe": [
    {
      "oemBrand": "GMC",
      "oemDisplayNo": "55 560 748"
    },
    {
      "oemBrand": "CHEVROLET",
      "oemDisplayNo": "55 594 651"
    },
    {
      "oemBrand": "HOLDEN",
      "oemDisplayNo": "55 594 651"
    },
    {
      "oemBrand": "GMC",
      "oemDisplayNo": "55353324"
    },
    {
      "oemBrand": "OPEL",
      "oemDisplayNo": "55353324"
    },
    {
      "oemBrand": "GMC",
      "oemDisplayNo": "55584685"
    },
    {
      "oemBrand": "ALFA ROMEO",
      "oemDisplayNo": "55594651"
    },
    {
      "oemBrand": "FIAT",
      "oemDisplayNo": "55594651"
    },
    {
      "oemBrand": "GMC",
      "oemDisplayNo": "55594651"
    },
    {
      "oemBrand": "OPEL",
      "oemDisplayNo": "55594651"
    },
    {
      "oemBrand": "VAUXHALL",
      "oemDisplayNo": "55594651"
    },
    {
      "oemBrand": "CHEVROLET",
      "oemDisplayNo": "55595651"
    },
    {
      "oemBrand": "OPEL",
      "oemDisplayNo": "5650359"
    },
    {
      "oemBrand": "OPEL",
      "oemDisplayNo": "6 50 155"
    },
    {
      "oemBrand": "GMC",
      "oemDisplayNo": "6 50 172"
    },
    {
      "oemBrand": "OPEL",
      "oemDisplayNo": "6 50 172"
    },
    {
      "oemBrand": "GMC",
      "oemDisplayNo": "6 50 173"
    },
    {
      "oemBrand": "ALFA ROMEO",
      "oemDisplayNo": "71744410"
    },
    {
      "oemBrand": "FIAT",
      "oemDisplayNo": "71744410"
    },
    {
      "oemBrand": "FIAT",
      "oemDisplayNo": "73504179"
    },
    {
      "oemBrand": "CHEVROLET",
      "oemDisplayNo": "93 185 674"
    },
    {
      "oemBrand": "HOLDEN",
      "oemDisplayNo": "93 185 674"
    },
    {
      "oemBrand": "GMC",
      "oemDisplayNo": "93185674"
    },
    {
      "oemBrand": "OPEL",
      "oemDisplayNo": "93185674"
    },
    {
      "oemBrand": "SAAB",
      "oemDisplayNo": "93185674"
    },
    {
      "oemBrand": "VAUXHALL",
      "oemDisplayNo": "93185674"
    },
    {
      "oemBrand": "DAEWOO",
      "oemDisplayNo": "93185674"
    },
    {
      "oemBrand": "BUICK",
      "oemDisplayNo": "93185674"
    },
    {
      "oemBrand": "GMC",
      "oemDisplayNo": "93190129"
    },
    {
      "oemBrand": "FIAT",
      "oemDisplayNo": "95526685"
    },
    {
      "oemBrand": "GMC",
      "oemDisplayNo": "95526685"
    },
    {
      "oemBrand": "CHEVROLET",
      "oemDisplayNo": "J93745801"
    }
  ],
  "ean": "4047024198845",
  "originalSKU": "55594651",
  "fetchedAt": "2026-03-17T16:49:36Z",
  "enrichedVia": "OEM (55594651)"
}